{"abandon":[],"aberrant":[],"abhor":[],"abiding":[],"abnormally":[],"abominable":[],"abort":[],"abridge":[],"abrupt":[],"absolute":[],"abundant":[],"accept":[],"access":[],"accompany":[],"accomplish":[],"accord":[],"account":[],"accustom":[],"achieve":[],"acid":[],"acoustic":[],"acquaint":[],"acquit":[],"active":[],"activity":[],"actual":["actuary"],"acute":[],"adapt":[],"addict":[],"adequate":[],"adherent":[],"adjust":[],"administrator":[],"admiral":["admirable","admiration"],"admission":[],"admit":[],"adolescent":[],"adopt":[],"adorn":[],"advance":[],"adventurer":[],"adverse":[],"adversity":[],"advert":[],"adviser":[],"affect":[],"affirm":[],"affluent":[],"afford":[],"afterward":[],"aggress":[],"agony":[],"agreement":[],"agriculturally":[],"alchemy":[],"alert":[],"alien":[],"align":[],"alleged":["allegory"],"allied":[],"allot":[],"allow":[],"alphabet":[],"alter":[],"alternate":[],"altruist":[],"aluminum":["aluminumal"],"amaze":[],"ambient":["ambition"],"ambiguous":[],"amend":[],"amenity":["amenable"],"American":[],"amuse":[],"analog":[],"anarchy":[],"ancestry":[],"animal":[],"annals":[],"announce":[],"annual":[],"antagonism":[],"anthropology":[],"antibiotic":[],"antiquity":[],"apart":[],"apology":[],"appal":[],"apparent":[],"appear":[],"applicant":[],"appoint":[],"appreciable":[],"apprehensive":[],"apprentice":[],"appropriate":[],"approximate":[],"arch":["archive"],"archaeology":[],"argument":[],"arid":[],"armor":[],"arrange":[],"ascend":[],"aspirant":[],"assail":[],"assassin":[],"assert":[],"assess":[],"assiduous":[],"assign":[],"assist":[],"assonant":[],"assort":[],"astonish":[],"astound":[],"astronomy":[],"atheist":[],"athletic":[],"atom":[],"atone":[],"atrocity":[],"attach":[],"attack":[],"attain":[],"attend":[],"attract":[],"attractively":[],"audacity":[],"audience":[],"audit":[],"authentic":[],"authority":[],"autobiography":[],"autonomy":[],"autumn":[],"avail":[],"avid":[],"avoid":[],"aware":[],"awful":[],"awkward":[],"bald":[],"bale":[],"balm":[],"bank":[],"barb":["barber"],"bare":[],"barrel":[],"base":[],"battle":[],"beak":["beaker"],"bear":[],"beat":[],"begin":[],"behavioral":[],"bell":["belly"],"bellow":["bellows"],"belt":["belter"],"beneficent":[],"beneficial":[],"benevolent":[],"benign":[],"bias":[],"bigamy":[],"biography":[],"biology":[],"biped":[],"bitterly":[],"blood":[],"blow":[],"blue":[],"blunt":[],"boat":[],"boil":[],"bombard":[],"boom":[],"botany":[],"both":["bother"],"bound":["boundary"],"bowl":[],"brand":[],"brave":[],"breath":[],"brief":[],"bright":[],"brilliant":[],"brisk":[],"broad":[],"broadcast":[],"brusque":[],"Buddhism":[],"build":[],"bulb":[],"bull":[],"bump":[],"burn":[],"butt":["butter"],"cacophony":[],"calculable":[],"call":["callous"],"Calvinist":[],"cancel":[],"candy":["candor"],"canon":[],"capacitor":[],"capacity":[],"capitalism":[],"captive":["captious"],"carbon":[],"care":["career"],"carnal":["carnation"],"carver":[],"catch":[],"catholic":[],"celebrated":[],"celebrity":[],"cell":["cellist"],"cement":[],"censorship":[],"cent":["center"],"centrally":[],"cerebral":[],"ceremony":[],"certain":[],"chalk":[],"challenger":[],"champion":[],"change":[],"char":["charity","chary"],"characterize":["characterise","characterization"],"charm":[],"chart":["charter"],"chastise":["chastity"],"chat":["chatter"],"cheap":[],"cheat":[],"check":[],"cheer":[],"chemist":["chemical"],"chief":[],"child":[],"chip":[],"chivalry":[],"chop":[],"choreograph":[],"chronology":[],"circuit":[],"citizen":[],"civil":[],"claim":[],"clam":["clamor"],"class":[],"classic":[],"clean":[],"clear":[],"clip":[],"close":[],"cloth":[],"cloud":[],"coal":["coalition"],"coast":[],"coat":[],"coherent":[],"coincident":[],"collaborator":[],"collar":[],"collect":[],"collier":["collision"],"colony":[],"color":[],"come":["comely"],"comfort":[],"comic":[],"command":[],"comment":["commence"],"commercialize":[],"commit":[],"commodity":["commodious"],"common":[],"communal":[],"compact":[],"companion":[],"compass":["compassion"],"compel":[],"competent":[],"competitor":[],"complacent":[],"complaisant":[],"complement":["completion"],"complete":[],"complex":[],"compliant":["compliment"],"complicity":["complication"],"composer":[],"comprehensive":[],"compress":[],"conceal":["conceive"],"concern":[],"concord":[],"concur":[],"condenser":[],"condescend":[],"conditioner":[],"condor":["condition"],"conducive":[],"conduct":[],"confess":[],"confident":[],"confine":[],"confirm":[],"conform":[],"confront":[],"conjugal":[],"connect":[],"consciously":[],"consequent":[],"conservative":[],"considering":[],"consist":["consent"],"constituent":[],"constrict":[],"construct":[],"consult":[],"contain":[],"contempt":[],"contend":[],"contentment":["contentious"],"contest":[],"continual":[],"contract":[],"contradict":[],"contrary":["contrition","contrive"],"contributor":[],"control":[],"convenient":[],"converse":[],"convert":[],"cook":[],"cool":[],"cord":[],"corn":["corner"],"corp":[],"corporal":["corporation"],"correct":[],"correspond":[],"cost":[],"counsel":[],"count":[],"court":["courteous","courtship"],"cover":[],"craftsman":[],"cramp":[],"creator":["creative"],"credentials":[],"credible":["credence"],"credit":[],"creep":[],"critic":[],"crook":[],"cross":[],"crowd":[],"crude":[],"crust":[],"crystallize":[],"curator":["curative"],"curl":[],"custom":[],"cyclist":["cyclical"],"dais":["daisy"],"damp":[],"dark":[],"daunt":[],"dead":[],"deal":[],"debt":[],"deceit":[],"deco":["decoy"],"decor":[],"decorator":[],"deduct":[],"deep":[],"defend":[],"defense":[],"defensive":[],"defer":[],"defiant":[],"definite":[],"deform":[],"deliberate":[],"delight":[],"demand":[],"democrat":[],"dense":[],"dent":[],"depart":[],"depend":[],"deport":[],"deposit":[],"depress":[],"descend":[],"desert":[],"desiccant":[],"design":["designation"],"desirable":[],"destiny":["destination"],"detach":[],"detail":[],"detect":[],"deter":[],"determinant":[],"detract":[],"develop":[],"deviant":[],"dexterous":[],"diction":[],"diet":[],"different":[],"differential":[],"difficult":[],"diffuse":[],"digest":[],"digit":[],"diligent":[],"direct":[],"dirt":[],"disagreement":[],"disappear":[],"disappoint":[],"discern":[],"disclaim":[],"discovery":[],"discuss":[],"disengage":[],"disgust":[],"disinterest":[],"dismiss":[],"dispensable":[],"displace":[],"disposal":["disposition"],"disproportionate":[],"disrupt":[],"dissenter":[],"distant":[],"distinct":[],"distinguish":[],"distract":[],"distress":[],"disturb":[],"diver":[],"divergent":[],"divisor":[],"documentary":[],"dole":[],"domestic":[],"dominant":[],"dorm":[],"doubt":[],"draw":[],"dread":[],"drum":[],"duct":[],"dump":["dumpling"],"duplicity":["duplication"],"dust":[],"dweller":[],"Dynamic":[],"eager":[],"earn":[],"earnest":[],"east":["easter"],"eastward":[],"ebullient":[],"eccentric":[],"eclectic":[],"ecology":[],"economic":[],"economy":[],"edit":[],"educable":[],"educator":[],"effect":[],"effectively":[],"efficacy":[],"eight":[],"elaborate":[],"elastic":[],"elder":[],"elect":[],"electric":[],"electronic":[],"elegant":[],"elemental":[],"elevator":[],"eloquent":[],"embarrass":[],"emergent":[],"emigrant":[],"eminent":[],"emotion":[],"emphasize":[],"employer":[],"enact":[],"encourage":[],"encroach":[],"endorse":[],"endow":[],"endurance":[],"energy":[],"engage":[],"engine":[],"engross":[],"enhance":[],"enjoyable":[],"enlarge":[],"enlighten":[],"enrich":[],"entangle":[],"entertain":[],"entreat":[],"entrepreneur":[],"entry":["entrance"],"enviable":["envision"],"environmentally":[],"equal":[],"equip":[],"equivalent":[],"establish":[],"etch":[],"ethic":[],"ethology":[],"even":["evening"],"ever":["every"],"evident":[],"exact":[],"exalt":[],"excel":[],"excess":[],"excite":[],"exciting":[],"exhaust":[],"exhibit":[],"exist":[],"expect":[],"expend":[],"experience":[],"experimental":[],"expert":[],"explicit":[],"exploit":[],"explorer":[],"export":[],"express":[],"externally":[],"extravagant":[],"extreme":[],"fabric":[],"facet":["facetious"],"fact":["factious"],"faint":[],"fair":["fairy"],"faith":[],"falcon":[],"fall":["fallible"],"fallacy":[],"FALSE":[],"familiar":[],"fantasy":[],"farm":[],"fascinated":[],"fashion":[],"fasten":[],"fatal":[],"fate":[],"fault":[],"favor":[],"favour":[],"fear":[],"feasible":[],"feature":[],"federal":[],"feed":[],"feel":[],"fellow":[],"ferry":["ferrous"],"fertility":[],"fervor":[],"feud":[],"fiction":[],"fierce":[],"fight":[],"film":[],"final":[],"financial":[],"find":[],"fine":[],"firework":[],"firm":[],"flash":[],"flat":["flatter"],"flesh":[],"flexible":[],"flick":[],"flip":[],"floral":[],"flow":["flower"],"fluent":[],"fluid":[],"focal":[],"follow":[],"force":[],"forecast":[],"foreign":[],"forerun":[],"forest":[],"forget":[],"form":[],"formally":["formalize"],"fort":["forty"],"fortunate":[],"fossil":[],"found":[],"fragrant":[],"frank":[],"free":[],"freight":[],"fresh":[],"fret":[],"friend":[],"fright":[],"frivolity":[],"front":[],"fruit":[],"full":[],"fund":[],"fungal":["fungible"],"furnish":[],"fuss":[],"gall":["gallant"],"garden":[],"gatherer":[],"general":[],"generally":[],"genetic":[],"gentleman":[],"genuine":[],"geography":[],"geology":[],"geometry":[],"German":[],"ghost":[],"gift":[],"gild":[],"glacier":[],"glamorous":[],"glass":[],"glassmaker":[],"gloom":[],"glory":[],"gloss":[],"good":[],"govern":[],"grace":[],"gradual":[],"grain":[],"graphic":[],"grass":[],"great":[],"greed":[],"green":[],"greet":[],"grievous":[],"grim":["grimy"],"grind":[],"ground":[],"grow":[],"guile":[],"guilt":[],"gull":["gully"],"gymnastic":[],"habit":[],"habitual":[],"hair":[],"hand":[],"handsome":[],"haphazard":[],"happily":[],"harass":[],"hard":[],"harm":[],"harmony":[],"harp":[],"harsh":[],"harvest":[],"hatch":[],"hate":[],"hazard":[],"head":[],"heal":[],"health":[],"hear":[],"heart":[],"heat":[],"heed":[],"help":[],"hero":[],"hesitant":[],"hexagon":[],"hide":["hideous"],"high":[],"hill":[],"hind":["hinder"],"hold":[],"home":[],"homemaker":[],"homestead":[],"hone":["honey"],"honest":[],"honor":[],"honour":[],"hope":[],"horror":[],"hospital":["hospitable"],"hospitalize":["hospitality"],"huge":[],"human":[],"humid":[],"humor":[],"hunt":[],"ideal":[],"identity":["identical"],"ideology":[],"idle":[],"ignorant":[],"illegal":["illegible"],"illustrator":[],"illustrious":["illustration"],"imaginary":[],"imitator":[],"immediate":[],"immense":[],"immigrant":[],"immobility":[],"impend":[],"impermanent":[],"impersonal":[],"impetus":[],"implicit":[],"import":[],"impossible":["imposition"],"impress":[],"impressionist":[],"imprison":[],"improve":[],"improvise":[],"inadequate":[],"incident":[],"incompatible":[],"incompetent":[],"incomplete":[],"incongruous":[],"incorrect":[],"incur":[],"indefinite":[],"independent":[],"indicant":[],"indicator":[],"indifferent":[],"indigent":[],"indignant":[],"indirect":[],"indiscriminate":[],"individually":[],"indolent":[],"induce":[],"induction":[],"industrially":[],"industry":[],"infect":[],"infer":[],"infinite":[],"infirm":[],"inflammable":[],"inform":[],"ingenuity":[],"inhabit":[],"inherit":[],"injury":[],"innocent":[],"innovator":[],"insight":[],"insist":[],"inspect":[],"inspiring":[],"instalment":["installation","installment"],"instant":["instability","instance"],"instinct":[],"instruct":[],"insurer":["insurance"],"integral":[],"intelligent":[],"intense":[],"intensity":["intensive"],"intent":[],"interact":[],"interdependent":[],"interest":[],"intermit":[],"intern":["internal"],"interpret":[],"intervening":[],"interview":[],"intimate":[],"intolerant":[],"intricate":[],"introspect":[],"invent":[],"inverse":[],"invest":[],"inviting":["invitation"],"involve":[],"iron":["irony"],"irregular":[],"irreverent":[],"irritable":[],"island":[],"jean":[],"jerk":[],"join":[],"journalist":[],"jubilant":[],"judge":[],"justified":[],"keen":[],"keep":[],"kind":[],"knowledge":[],"labor":[],"labour":[],"land":[],"large":[],"last":[],"late":[],"later":["lateral"],"laud":[],"lead":[],"leaf":[],"leak":[],"lean":[],"learn":[],"legal":[],"legend":[],"legislator":[],"legitimate":[],"leisure":[],"length":[],"libel":[],"liberal":[],"light":[],"like":[],"limit":[],"ling":["linger"],"lingual":[],"linguistic":[],"list":["listless"],"listen":[],"liter":[],"literally":["literalness"],"lithograph":[],"litigant":[],"live":[],"local":[],"lock":[],"locomotor":[],"loft":[],"logic":[],"London":[],"lone":[],"long":[],"loose":[],"lord":[],"loud":[],"love":[],"loyal":[],"luck":[],"luminous":[],"lust":[],"luxury":[],"lyric":[],"magic":[],"magnet":[],"magnificent":[],"main":[],"major":[],"malign":[],"malleable":[],"manage":[],"manifest":[],"margin":[],"mark":[],"market":[],"marsh":["marshal"],"marvel":[],"Marxism":[],"mass":[],"mast":["master"],"materialism":[],"math":[],"maturity":[],"mean":[],"meaningful":[],"measure":[],"meat":[],"mechanic":[],"mechanism":[],"medical":[],"meet":[],"melody":[],"memory":[],"merciful":[],"mere":[],"mess":[],"metabolism":[],"metalwork":[],"meteorology":[],"method":[],"might":[],"migrant":[],"mild":[],"military":[],"milk":[],"miner":["mineral"],"mineralize":[],"minimal":[],"minor":[],"minute":[],"miser":[],"mislead":[],"mismanage":[],"miss":[],"mission":[],"mist":["mister"],"misunderstand":[],"mobility":[],"mode":[],"moderate":[],"modern":[],"modest":[],"moment":[],"monarch":[],"monogamy":[],"monotony":[],"month":[],"mood":[],"moral":[],"morphology":[],"mortal":["mortise"],"most":[],"moth":["mother"],"motion":[],"mould":[],"mountain":[],"mourn":[],"mouth":[],"move":[],"multiplicity":[],"munificent":[],"murderer":[],"muscular":[],"music":[],"mutually":[],"mystery":[],"myth":[],"mythology":[],"name":[],"narrator":[],"narrow":[],"nation":[],"nationally":[],"naturally":[],"navigable":[],"near":[],"neat":[],"necessary":[],"need":[],"negligent":[],"neighbour":[],"neology":[],"nest":[],"Netherland":[],"neutrality":[],"nomad":[],"nonconformity":[],"norm":[],"normally":[],"northern":[],"northward":[],"notice":[],"nourish":[],"novel":[],"numb":["number"],"numeral":[],"nutrient":[],"nutritional":[],"nutritive":[],"obedient":[],"object":[],"observer":[],"obsess":[],"occupy":[],"occur":[],"oceanography":[],"odor":[],"offer":[],"officer":["officious"],"onrush":[],"open":[],"operant":[],"opportunity":[],"opposed":[],"opposite":[],"oppress":[],"optic":[],"optimal":[],"option":[],"orator":[],"orbit":[],"order":[],"ordinal":[],"organ":[],"orient":[],"origin":[],"originally":[],"ornamental":[],"orthodox":[],"outdo":["outdoor"],"outskirt":[],"outward":[],"over":[],"oversea":[],"overwhelm":[],"owner":[],"oxidizer":[],"pack":[],"page":["pageant"],"pain":[],"paint":[],"pant":["pants"],"paradox":[],"parent":[],"park":[],"part":[],"participant":[],"particular":[],"pass":["passive"],"pastoralist":[],"patch":[],"pathology":[],"patient":[],"patriarch":[],"patriot":[],"patron":[],"patty":["patter"],"pave":[],"peace":[],"pear":["pearly"],"peculiar":[],"pedagogy":[],"peer":[],"penury":[],"perceptive":[],"percussion":[],"perfect":[],"perform":[],"peril":[],"period":[],"periodic":[],"periphery":[],"perish":[],"permanent":[],"permeable":[],"permission":[],"perplex":[],"persistent":[],"person":[],"personally":[],"perspicacity":[],"perspicuous":[],"pertinacity":[],"philanthropy":[],"philosophy":[],"photograph":[],"physic":[],"physiology":[],"pick":[],"pill":["pillory"],"pivot":[],"plaint":[],"planet":[],"plant":[],"plastic":[],"play":[],"pleased":["pleasant","pleasing"],"plenty":[],"plumb":[],"point":[],"poison":[],"polar":[],"polite":[],"politic":[],"polygamy":[],"pomp":[],"pond":["ponder"],"poor":[],"popular":[],"populous":[],"port":["portent"],"portrait":[],"posit":[],"possess":[],"possible":[],"post":[],"potentially":[],"power":[],"practically":[],"practise":["practical"],"pray":[],"preceding":[],"precise":["precious"],"predator":[],"predict":[],"predominant":[],"preeminent":[],"preference":[],"premature":[],"preoccupy":[],"preponderant":[],"prepossess":[],"preschool":[],"prescient":[],"presentient":[],"presently":["presentation"],"press":["presence","present"],"prevalent":[],"prevent":["previous"],"preventive":[],"price":[],"prick":[],"prim":[],"print":[],"printmaker":[],"prior":[],"prison":[],"private":[],"probity":["probability","probable","probation"],"process":[],"prodigy":["prodigal","prodigious"],"producer":["production"],"product":[],"profess":[],"profit":[],"profound":[],"program":[],"progress":[],"prohibit":[],"project":[],"prolong":[],"prominent":[],"prompt":[],"propel":[],"proportionate":[],"proposal":["proposition"],"propriety":["proprietor"],"prospect":[],"prosperity":[],"protect":[],"proud":[],"provided":["providence","provident"],"psychiatry":[],"psychology":[],"public":[],"publish":[],"pulverize":[],"punctual":["punctuation"],"punish":[],"pure":[],"puritan":[],"purpose":[],"quart":[],"quick":[],"quiet":[],"quit":[],"radial":["radiance","radiant","radiation"],"rain":[],"ranch":[],"random":[],"rapid":[],"rare":[],"ration":["rational"],"rationally":["rationalism","rationality","rationalization","rationalize"],"raven":[],"reach":[],"react":[],"read":["ready"],"real":[],"reap":["reapply"],"reason":[],"rebel":[],"recent":[],"receptor":["receptive"],"recess":[],"reciprocal":[],"recital":[],"reck":[],"recognise":[],"recommend":[],"record":[],"recreant":["recreation"],"recruit":[],"recur":[],"refer":[],"refine":[],"reflect":[],"reform":[],"refract":[],"refresh":[],"regard":[],"region":[],"regionalist":[],"regret":[],"regular":[],"regulator":[],"reimburse":[],"relational":[],"relax":[],"relay":["relation"],"relevant":[],"reliant":[],"relieved":[],"reluctant":[],"remain":[],"remark":[],"remind":[],"remiss":[],"remorse":[],"rend":[],"renew":[],"renown":[],"rent":[],"repair":[],"reparable":[],"repeat":[],"repel":[],"replace":[],"replenish":[],"reply":["replant"],"report":[],"repress":["represent"],"reputable":[],"require":[],"research":[],"resent":[],"reserved":[],"resident":[],"resign":[],"resilient":[],"resist":[],"resource":[],"respect":[],"respond":[],"responsive":[],"rest":[],"restrict":[],"result":[],"retail":[],"retire":[],"retrospect":[],"reversal":[],"review":[],"revitalize":[],"revolutionary":[],"reward":[],"rhythm":[],"rich":[],"right":[],"rigid":[],"rigor":[],"riot":[],"risk":[],"rock":[],"roll":[],"Roman":[],"romantic":[],"roost":[],"root":[],"rough":[],"routine":[],"ruin":[],"runner":[],"safe":[],"sagacity":[],"sail":[],"sale":[],"salinity":[],"salt":[],"salutary":[],"salvage":[],"sand":["sandal"],"satirist":[],"saucy":["saucer"],"scan":[],"scant":[],"scar":["scared","scary"],"scarce":[],"scat":["scatter"],"scholar":[],"scorn":[],"scrap":[],"screen":[],"scrutiny":[],"sculpt":[],"seal":[],"season":[],"second":[],"secret":["secretary"],"sect":[],"section":[],"secure":[],"sediment":["sedition"],"sedimentary":[],"seed":[],"seek":[],"select":[],"self":[],"sell":[],"send":[],"sense":[],"sensor":["sensation","sensibility","sensible","sensory"],"sensual":["sensuous"],"sentient":["sentiment"],"separable":["separation"],"separate":["separately"],"sequent":["sequence"],"series":["serial","serious"],"sermon":[],"server":[],"service":[],"settle":[],"several":["severity"],"severe":[],"shadow":[],"shame":[],"shape":[],"sharp":[],"sharpen":[],"shift":[],"shin":[],"ship":[],"shoemaker":[],"shoot":[],"shop":[],"short":[],"should":["shoulder"],"show":["shower"],"showman":[],"shrub":[],"shut":[],"sick":[],"sign":[],"significant":[],"sill":["silly"],"similar":[],"sincere":[],"sing":["singly"],"skilled":[],"sled":[],"sleep":[],"slight":[],"slim":["slimy"],"slip":[],"sloth":[],"slow":[],"sluggish":[],"smelt":[],"smoky":[],"smooth":[],"sneak":[],"snow":[],"social":[],"socially":["socialism","socialist","socialization","socialize"],"sociology":[],"sock":[],"soft":[],"soil":[],"sole":[],"solicit":[],"solid":[],"solo":[],"sorrow":[],"sound":[],"southern":[],"southward":[],"souvenir":[],"space":[],"sparse":[],"speak":[],"special":[],"specially":[],"specific":[],"spectacular":[],"speculator":[],"speed":[],"spheroid":[],"spin":["spinal"],"spine":[],"spoon":[],"spur":["spurious"],"square":[],"stability":[],"stag":["stagger","stagy"],"staggered":[],"stain":[],"stair":[],"standard":[],"star":["starling"],"start":["startling"],"state":[],"station":[],"statistic":[],"status":["statuary"],"steadfast":[],"stealth":[],"steam":[],"step":[],"stick":[],"stimulant":[],"sting":["stingy"],"stock":["stocking","stocky"],"store":["storey"],"storm":[],"storyteller":[],"stress":[],"stretch":[],"strict":[],"string":["stringent"],"strip":["stripling"],"strong":[],"stubborn":[],"stud":[],"subject":[],"subsidy":[],"subtract":[],"suburban":[],"success":[],"succinct":[],"sudden":[],"suggest":[],"suit":[],"summarize":[],"summer":["summary"],"superb":[],"superintend":[],"supervisor":[],"supper":["supply"],"supple":["supplement"],"supplementary":["supplementation"],"support":[],"supreme":[],"surround":[],"survival":[],"suspend":[],"sustain":[],"swamp":[],"sweat":["sweater"],"sweep":[],"sweet":[],"swift":[],"swim":[],"symbol":[],"symmetry":[],"sympathy":[],"symphony":[],"synchronize":[],"synonym":[],"systematize":[],"tactic":[],"tail":["tailor"],"talent":[],"tall":["tally"],"tang":[],"tank":[],"taste":[],"teach":[],"technology":[],"tectonic":[],"telecommuter":[],"tell":[],"tempera":["temperament"],"temporal":[],"tempt":[],"tenacity":[],"tend":[],"terminal":[],"terror":[],"terrorist":[],"thank":[],"their":[],"theory":[],"therapy":[],"thick":[],"thin":[],"think":[],"thirst":[],"thorn":[],"thorough":[],"thought":[],"thresh":[],"thrift":[],"thriller":[],"tight":[],"time":[],"timid":[],"tired":[],"toad":[],"tolerant":[],"toolmaker":[],"topic":[],"topography":[],"total":[],"tour":[],"toward":[],"tower":[],"tract":[],"trader":["tradition"],"train":[],"trait":["traitor"],"tranquil":[],"transcend":[],"transform":[],"transgress":[],"transient":[],"transit":[],"transmit":[],"transport":[],"trap":[],"travel":[],"treachery":[],"treasury":[],"treat":[],"tree":[],"trench":["trenchant"],"trespass":[],"triumph":[],"trumpet":[],"turbulent":[],"turn":[],"tutor":[],"tyranny":[],"ultimate":[],"unanimous":[],"under":[],"understand":[],"unemployed":[],"uneven":[],"unfair":[],"unfortunate":[],"uniform":[],"uninhabited":[],"union":[],"unique":[],"unit":[],"universal":[],"universally":[],"unlike":[],"unpredictable":[],"unsure":[],"unused":["unusable"],"unwillingly":[],"uproar":[],"upward":[],"urban":[],"useful":[],"usual":[],"usury":[],"utility":[],"utter":[],"vacuous":[],"vague":[],"valid":[],"valor":[],"vapor":[],"varied":[],"vast":[],"vegetal":[],"velvet":[],"venom":[],"veracity":[],"verb":[],"verbally":[],"verity":[],"vibrant":[],"victim":[],"view":[],"vigilant":[],"vigor":[],"violent":[],"violin":[],"virgin":[],"virtu":["virtual"],"visit":[],"visually":[],"vital":[],"vivacity":[],"vocal":[],"vulnerable":[],"wait":[],"walk":[],"wand":["wander"],"warm":[],"warn":[],"waste":[],"watch":[],"water":[],"weak":[],"wealth":[],"wear":["weary"],"weed":[],"week":[],"weight":[],"western":[],"westward":[],"whisky":["whisker"],"wick":["wicked"],"wide":[],"will":[],"willingly":[],"wind":[],"wing":[],"wire":[],"wish":[],"with":["wither"],"withdraw":[],"wood":[],"woodcut":[],"woodworker":[],"work":[],"workman":[],"world":[],"worship":[],"worth":[],"wound":[],"wrap":[],"wretch":[],"writer":[],"year":[],"your":[],"zeal":[],"zoology":[]}