{
  "version": 1,
  "entries": {
    "banked_cloze-bp-cet4-10asoyz": {
      "rowId": "banked_cloze-bp-cet4-10asoyz",
      "type": "banked_cloze",
      "shapeIssues": [],
      "updatedAt": "2026-06-17T22:41:02.269Z"
    },
    "banked_cloze-bp-cet4-10mjsqu": {
      "rowId": "banked_cloze-bp-cet4-10mjsqu",
      "type": "banked_cloze",
      "shapeIssues": [],
      "updatedAt": "2026-06-17T22:41:02.272Z"
    },
    "banked_cloze-bp-cet4-10qooc6": {
      "rowId": "banked_cloze-bp-cet4-10qooc6",
      "type": "banked_cloze",
      "shapeIssues": [],
      "updatedAt": "2026-06-17T22:41:02.272Z"
    },
    "banked_cloze-bp-cet4-10thho6": {
      "rowId": "banked_cloze-bp-cet4-10thho6",
      "type": "banked_cloze",
      "shapeIssues": [],
      "updatedAt": "2026-06-17T22:41:02.273Z"
    },
    "banked_cloze-bp-cet4-10y7zxv": {
      "rowId": "banked_cloze-bp-cet4-10y7zxv",
      "type": "banked_cloze",
      "shapeIssues": [],
      "updatedAt": "2026-06-17T22:41:02.274Z"
    },
    "banked_cloze-bp-cet4-115fefh": {
      "rowId": "banked_cloze-bp-cet4-115fefh",
      "type": "banked_cloze",
      "shapeIssues": [],
      "updatedAt": "2026-06-17T22:41:02.274Z"
    },
    "banked_cloze-bp-cet4-116vnxg": {
      "rowId": "banked_cloze-bp-cet4-116vnxg",
      "type": "banked_cloze",
      "shapeIssues": [],
      "updatedAt": "2026-06-17T22:41:02.274Z"
    },
    "banked_cloze-bp-cet4-12hxn3l": {
      "rowId": "banked_cloze-bp-cet4-12hxn3l",
      "type": "banked_cloze",
      "shapeIssues": [],
      "updatedAt": "2026-06-17T22:41:02.275Z"
    },
    "banked_cloze-bp-cet4-13g7yuu": {
      "rowId": "banked_cloze-bp-cet4-13g7yuu",
      "type": "banked_cloze",
      "shapeIssues": [],
      "updatedAt": "2026-06-17T22:41:02.276Z"
    },
    "banked_cloze-bp-cet4-147m7t2": {
      "rowId": "banked_cloze-bp-cet4-147m7t2",
      "type": "banked_cloze",
      "shapeIssues": [],
      "updatedAt": "2026-06-17T22:41:02.276Z"
    },
    "banked_cloze-bp-cet4-14jb9nt": {
      "rowId": "banked_cloze-bp-cet4-14jb9nt",
      "type": "banked_cloze",
      "shapeIssues": [],
      "updatedAt": "2026-06-17T22:41:02.277Z"
    },
    "banked_cloze-bp-cet4-14pqnks": {
      "rowId": "banked_cloze-bp-cet4-14pqnks",
      "type": "banked_cloze",
      "shapeIssues": [],
      "updatedAt": "2026-06-17T22:41:02.279Z"
    },
    "banked_cloze-bp-cet4-14t18fy": {
      "rowId": "banked_cloze-bp-cet4-14t18fy",
      "type": "banked_cloze",
      "shapeIssues": [],
      "updatedAt": "2026-06-17T22:41:02.280Z"
    },
    "banked_cloze-bp-cet4-14tcv0n": {
      "rowId": "banked_cloze-bp-cet4-14tcv0n",
      "type": "banked_cloze",
      "shapeIssues": [],
      "updatedAt": "2026-06-17T22:41:02.281Z"
    },
    "banked_cloze-bp-cet4-150nbrb": {
      "rowId": "banked_cloze-bp-cet4-150nbrb",
      "type": "banked_cloze",
      "shapeIssues": [],
      "updatedAt": "2026-06-17T22:41:02.281Z"
    },
    "banked_cloze-bp-cet4-15a4c4q": {
      "rowId": "banked_cloze-bp-cet4-15a4c4q",
      "type": "banked_cloze",
      "shapeIssues": [],
      "updatedAt": "2026-06-17T22:41:02.282Z"
    },
    "banked_cloze-bp-cet4-15t5jmy": {
      "rowId": "banked_cloze-bp-cet4-15t5jmy",
      "type": "banked_cloze",
      "shapeIssues": [],
      "updatedAt": "2026-06-17T22:41:02.283Z"
    },
    "banked_cloze-bp-cet4-160akbr": {
      "rowId": "banked_cloze-bp-cet4-160akbr",
      "type": "banked_cloze",
      "shapeIssues": [],
      "updatedAt": "2026-06-17T22:41:02.284Z"
    },
    "banked_cloze-bp-cet4-17684in": {
      "rowId": "banked_cloze-bp-cet4-17684in",
      "type": "banked_cloze",
      "shapeIssues": [],
      "updatedAt": "2026-06-17T22:41:02.285Z"
    },
    "banked_cloze-bp-cet4-17cjj1s": {
      "rowId": "banked_cloze-bp-cet4-17cjj1s",
      "type": "banked_cloze",
      "shapeIssues": [],
      "updatedAt": "2026-06-17T22:41:02.286Z"
    },
    "banked_cloze-bp-cet4-17dhhg4": {
      "rowId": "banked_cloze-bp-cet4-17dhhg4",
      "type": "banked_cloze",
      "shapeIssues": [],
      "updatedAt": "2026-06-17T22:41:02.286Z"
    },
    "banked_cloze-bp-cet4-17wraix": {
      "rowId": "banked_cloze-bp-cet4-17wraix",
      "type": "banked_cloze",
      "shapeIssues": [],
      "updatedAt": "2026-06-17T22:41:02.287Z"
    },
    "banked_cloze-bp-cet4-187mhqf": {
      "rowId": "banked_cloze-bp-cet4-187mhqf",
      "type": "banked_cloze",
      "shapeIssues": [],
      "updatedAt": "2026-06-17T22:41:02.287Z"
    },
    "banked_cloze-bp-cet4-19e6nuv": {
      "rowId": "banked_cloze-bp-cet4-19e6nuv",
      "type": "banked_cloze",
      "shapeIssues": [],
      "updatedAt": "2026-06-17T22:41:02.288Z"
    },
    "banked_cloze-bp-cet4-19p9nis": {
      "rowId": "banked_cloze-bp-cet4-19p9nis",
      "type": "banked_cloze",
      "shapeIssues": [],
      "updatedAt": "2026-06-17T22:41:02.289Z"
    },
    "banked_cloze-bp-cet4-1aoh8u7": {
      "rowId": "banked_cloze-bp-cet4-1aoh8u7",
      "type": "banked_cloze",
      "shapeIssues": [],
      "updatedAt": "2026-06-17T22:41:02.290Z"
    },
    "banked_cloze-bp-cet4-1b24zdm": {
      "rowId": "banked_cloze-bp-cet4-1b24zdm",
      "type": "banked_cloze",
      "shapeIssues": [],
      "updatedAt": "2026-06-17T22:41:02.291Z"
    },
    "banked_cloze-bp-cet4-1ba1syi": {
      "rowId": "banked_cloze-bp-cet4-1ba1syi",
      "type": "banked_cloze",
      "shapeIssues": [],
      "updatedAt": "2026-06-17T22:41:02.291Z"
    },
    "banked_cloze-bp-cet4-1cn96uu": {
      "rowId": "banked_cloze-bp-cet4-1cn96uu",
      "type": "banked_cloze",
      "shapeIssues": [],
      "updatedAt": "2026-06-17T22:41:02.292Z"
    },
    "banked_cloze-bp-cet4-1cnd53h": {
      "rowId": "banked_cloze-bp-cet4-1cnd53h",
      "type": "banked_cloze",
      "shapeIssues": [],
      "updatedAt": "2026-06-17T22:41:02.293Z"
    },
    "banked_cloze-bp-cet4-1cqu385": {
      "rowId": "banked_cloze-bp-cet4-1cqu385",
      "type": "banked_cloze",
      "shapeIssues": [],
      "updatedAt": "2026-06-17T22:41:02.293Z"
    },
    "banked_cloze-bp-cet4-1csopfh": {
      "rowId": "banked_cloze-bp-cet4-1csopfh",
      "type": "banked_cloze",
      "shapeIssues": [],
      "updatedAt": "2026-06-17T22:41:02.294Z"
    },
    "banked_cloze-bp-cet4-1dz2hrv": {
      "rowId": "banked_cloze-bp-cet4-1dz2hrv",
      "type": "banked_cloze",
      "shapeIssues": [],
      "updatedAt": "2026-06-17T22:41:02.295Z"
    },
    "banked_cloze-bp-cet4-1e3kl1v": {
      "rowId": "banked_cloze-bp-cet4-1e3kl1v",
      "type": "banked_cloze",
      "shapeIssues": [],
      "updatedAt": "2026-06-17T22:41:02.295Z"
    },
    "banked_cloze-bp-cet4-1ega4sv": {
      "rowId": "banked_cloze-bp-cet4-1ega4sv",
      "type": "banked_cloze",
      "shapeIssues": [],
      "updatedAt": "2026-06-17T22:41:02.296Z"
    },
    "banked_cloze-bp-cet4-1egos23": {
      "rowId": "banked_cloze-bp-cet4-1egos23",
      "type": "banked_cloze",
      "shapeIssues": [],
      "updatedAt": "2026-06-17T22:41:02.297Z"
    },
    "banked_cloze-bp-cet4-1ew8qwv": {
      "rowId": "banked_cloze-bp-cet4-1ew8qwv",
      "type": "banked_cloze",
      "shapeIssues": [],
      "updatedAt": "2026-06-17T22:41:02.297Z"
    },
    "banked_cloze-bp-cet4-1f9usf2": {
      "rowId": "banked_cloze-bp-cet4-1f9usf2",
      "type": "banked_cloze",
      "shapeIssues": [],
      "updatedAt": "2026-06-17T22:41:02.298Z"
    },
    "banked_cloze-bp-cet4-1fbiqd6": {
      "rowId": "banked_cloze-bp-cet4-1fbiqd6",
      "type": "banked_cloze",
      "shapeIssues": [],
      "updatedAt": "2026-06-17T22:41:02.298Z"
    },
    "banked_cloze-bp-cet4-1g88kqh": {
      "rowId": "banked_cloze-bp-cet4-1g88kqh",
      "type": "banked_cloze",
      "shapeIssues": [],
      "updatedAt": "2026-06-17T22:41:02.298Z"
    },
    "banked_cloze-bp-cet4-1juuwgi": {
      "rowId": "banked_cloze-bp-cet4-1juuwgi",
      "type": "banked_cloze",
      "shapeIssues": [],
      "updatedAt": "2026-06-17T22:41:02.299Z"
    },
    "banked_cloze-bp-cet4-1l68c2d": {
      "rowId": "banked_cloze-bp-cet4-1l68c2d",
      "type": "banked_cloze",
      "shapeIssues": [],
      "updatedAt": "2026-06-17T22:41:02.299Z"
    },
    "banked_cloze-bp-cet4-1lqgw9n": {
      "rowId": "banked_cloze-bp-cet4-1lqgw9n",
      "type": "banked_cloze",
      "shapeIssues": [],
      "updatedAt": "2026-06-17T22:41:02.300Z"
    },
    "banked_cloze-bp-cet4-1lwaq9g": {
      "rowId": "banked_cloze-bp-cet4-1lwaq9g",
      "type": "banked_cloze",
      "shapeIssues": [],
      "updatedAt": "2026-06-17T22:41:02.300Z"
    },
    "banked_cloze-bp-cet4-1lwvem2": {
      "rowId": "banked_cloze-bp-cet4-1lwvem2",
      "type": "banked_cloze",
      "shapeIssues": [],
      "updatedAt": "2026-06-17T22:41:02.301Z"
    },
    "banked_cloze-bp-cet4-1lyuvwr": {
      "rowId": "banked_cloze-bp-cet4-1lyuvwr",
      "type": "banked_cloze",
      "shapeIssues": [],
      "updatedAt": "2026-06-17T22:41:02.301Z"
    },
    "banked_cloze-bp-cet4-1m74v0c": {
      "rowId": "banked_cloze-bp-cet4-1m74v0c",
      "type": "banked_cloze",
      "shapeIssues": [],
      "updatedAt": "2026-06-17T22:41:02.302Z"
    },
    "banked_cloze-bp-cet4-1mwu10j": {
      "rowId": "banked_cloze-bp-cet4-1mwu10j",
      "type": "banked_cloze",
      "shapeIssues": [],
      "updatedAt": "2026-06-17T22:41:02.302Z"
    },
    "banked_cloze-bp-cet4-1ojqovd": {
      "rowId": "banked_cloze-bp-cet4-1ojqovd",
      "type": "banked_cloze",
      "shapeIssues": [],
      "updatedAt": "2026-06-17T22:41:02.303Z"
    },
    "banked_cloze-bp-cet4-1olt6pk": {
      "rowId": "banked_cloze-bp-cet4-1olt6pk",
      "type": "banked_cloze",
      "shapeIssues": [],
      "updatedAt": "2026-06-17T22:41:02.304Z"
    },
    "banked_cloze-bp-cet4-1pzmuex": {
      "rowId": "banked_cloze-bp-cet4-1pzmuex",
      "type": "banked_cloze",
      "shapeIssues": [],
      "updatedAt": "2026-06-17T22:41:02.304Z"
    },
    "banked_cloze-bp-cet4-1qzegkm": {
      "rowId": "banked_cloze-bp-cet4-1qzegkm",
      "type": "banked_cloze",
      "shapeIssues": [],
      "updatedAt": "2026-06-17T22:41:02.305Z"
    },
    "banked_cloze-bp-cet4-1rxz8ru": {
      "rowId": "banked_cloze-bp-cet4-1rxz8ru",
      "type": "banked_cloze",
      "shapeIssues": [],
      "updatedAt": "2026-06-17T22:41:02.305Z"
    },
    "banked_cloze-bp-cet4-1s0lr8w": {
      "rowId": "banked_cloze-bp-cet4-1s0lr8w",
      "type": "banked_cloze",
      "shapeIssues": [],
      "updatedAt": "2026-06-17T22:41:02.306Z"
    },
    "banked_cloze-bp-cet4-1t4pqus": {
      "rowId": "banked_cloze-bp-cet4-1t4pqus",
      "type": "banked_cloze",
      "shapeIssues": [],
      "updatedAt": "2026-06-17T22:41:02.306Z"
    },
    "banked_cloze-bp-cet4-1t9sk5o": {
      "rowId": "banked_cloze-bp-cet4-1t9sk5o",
      "type": "banked_cloze",
      "shapeIssues": [],
      "updatedAt": "2026-06-17T22:41:02.307Z"
    },
    "banked_cloze-bp-cet4-1tm2wa9": {
      "rowId": "banked_cloze-bp-cet4-1tm2wa9",
      "type": "banked_cloze",
      "shapeIssues": [],
      "updatedAt": "2026-06-17T22:41:02.308Z"
    },
    "banked_cloze-bp-cet4-1ts2y6t": {
      "rowId": "banked_cloze-bp-cet4-1ts2y6t",
      "type": "banked_cloze",
      "shapeIssues": [],
      "updatedAt": "2026-06-17T22:41:02.309Z"
    },
    "banked_cloze-bp-cet4-1ueg1ph": {
      "rowId": "banked_cloze-bp-cet4-1ueg1ph",
      "type": "banked_cloze",
      "shapeIssues": [],
      "updatedAt": "2026-06-17T22:41:02.309Z"
    },
    "banked_cloze-bp-cet4-1v2zmgv": {
      "rowId": "banked_cloze-bp-cet4-1v2zmgv",
      "type": "banked_cloze",
      "shapeIssues": [],
      "updatedAt": "2026-06-17T22:41:02.310Z"
    },
    "banked_cloze-bp-cet4-1vjl43c": {
      "rowId": "banked_cloze-bp-cet4-1vjl43c",
      "type": "banked_cloze",
      "shapeIssues": [],
      "updatedAt": "2026-06-17T22:41:02.310Z"
    },
    "banked_cloze-bp-cet4-1vkqxe6": {
      "rowId": "banked_cloze-bp-cet4-1vkqxe6",
      "type": "banked_cloze",
      "shapeIssues": [],
      "updatedAt": "2026-06-17T22:41:02.311Z"
    },
    "banked_cloze-bp-cet4-1wb88yr": {
      "rowId": "banked_cloze-bp-cet4-1wb88yr",
      "type": "banked_cloze",
      "shapeIssues": [],
      "updatedAt": "2026-06-17T22:41:02.311Z"
    },
    "banked_cloze-bp-cet4-1xr528x": {
      "rowId": "banked_cloze-bp-cet4-1xr528x",
      "type": "banked_cloze",
      "shapeIssues": [],
      "updatedAt": "2026-06-17T22:41:02.312Z"
    },
    "banked_cloze-bp-cet4-1yeozei": {
      "rowId": "banked_cloze-bp-cet4-1yeozei",
      "type": "banked_cloze",
      "shapeIssues": [],
      "updatedAt": "2026-06-17T22:41:02.312Z"
    },
    "banked_cloze-bp-cet4-1ygfbb5": {
      "rowId": "banked_cloze-bp-cet4-1ygfbb5",
      "type": "banked_cloze",
      "shapeIssues": [],
      "updatedAt": "2026-06-17T22:41:02.312Z"
    },
    "banked_cloze-bp-cet4-2om6t4": {
      "rowId": "banked_cloze-bp-cet4-2om6t4",
      "type": "banked_cloze",
      "shapeIssues": [],
      "updatedAt": "2026-06-17T22:41:02.313Z"
    },
    "banked_cloze-bp-cet4-59bs7": {
      "rowId": "banked_cloze-bp-cet4-59bs7",
      "type": "banked_cloze",
      "shapeIssues": [],
      "updatedAt": "2026-06-17T22:41:02.313Z"
    },
    "banked_cloze-bp-cet4-5lxtbh": {
      "rowId": "banked_cloze-bp-cet4-5lxtbh",
      "type": "banked_cloze",
      "shapeIssues": [],
      "updatedAt": "2026-06-17T22:41:02.314Z"
    },
    "banked_cloze-bp-cet4-60bu0h": {
      "rowId": "banked_cloze-bp-cet4-60bu0h",
      "type": "banked_cloze",
      "shapeIssues": [],
      "updatedAt": "2026-06-17T22:41:02.314Z"
    },
    "banked_cloze-bp-cet4-6jh8yr": {
      "rowId": "banked_cloze-bp-cet4-6jh8yr",
      "type": "banked_cloze",
      "shapeIssues": [],
      "updatedAt": "2026-06-17T22:41:02.315Z"
    },
    "banked_cloze-bp-cet4-6jz189": {
      "rowId": "banked_cloze-bp-cet4-6jz189",
      "type": "banked_cloze",
      "shapeIssues": [],
      "updatedAt": "2026-06-17T22:41:02.315Z"
    },
    "banked_cloze-bp-cet4-79p06a": {
      "rowId": "banked_cloze-bp-cet4-79p06a",
      "type": "banked_cloze",
      "shapeIssues": [],
      "updatedAt": "2026-06-17T22:41:02.316Z"
    },
    "banked_cloze-bp-cet4-7bire7": {
      "rowId": "banked_cloze-bp-cet4-7bire7",
      "type": "banked_cloze",
      "shapeIssues": [],
      "updatedAt": "2026-06-17T22:41:02.316Z"
    },
    "banked_cloze-bp-cet4-7m6p93": {
      "rowId": "banked_cloze-bp-cet4-7m6p93",
      "type": "banked_cloze",
      "shapeIssues": [],
      "updatedAt": "2026-06-17T22:41:02.317Z"
    },
    "banked_cloze-bp-cet4-85ymg3": {
      "rowId": "banked_cloze-bp-cet4-85ymg3",
      "type": "banked_cloze",
      "shapeIssues": [],
      "updatedAt": "2026-06-17T22:41:02.317Z"
    },
    "banked_cloze-bp-cet4-97w8l8": {
      "rowId": "banked_cloze-bp-cet4-97w8l8",
      "type": "banked_cloze",
      "shapeIssues": [],
      "updatedAt": "2026-06-17T22:41:02.318Z"
    },
    "banked_cloze-bp-cet4-9lrpzo": {
      "rowId": "banked_cloze-bp-cet4-9lrpzo",
      "type": "banked_cloze",
      "shapeIssues": [],
      "updatedAt": "2026-06-17T22:41:02.318Z"
    },
    "banked_cloze-bp-cet4-9mkq0d": {
      "rowId": "banked_cloze-bp-cet4-9mkq0d",
      "type": "banked_cloze",
      "shapeIssues": [],
      "updatedAt": "2026-06-17T22:41:02.319Z"
    },
    "banked_cloze-bp-cet4-abb8sp": {
      "rowId": "banked_cloze-bp-cet4-abb8sp",
      "type": "banked_cloze",
      "shapeIssues": [],
      "updatedAt": "2026-06-17T22:41:02.319Z"
    },
    "banked_cloze-bp-cet4-b3v0v9": {
      "rowId": "banked_cloze-bp-cet4-b3v0v9",
      "type": "banked_cloze",
      "shapeIssues": [],
      "updatedAt": "2026-06-17T22:41:02.320Z"
    },
    "banked_cloze-bp-cet4-bi76bx": {
      "rowId": "banked_cloze-bp-cet4-bi76bx",
      "type": "banked_cloze",
      "shapeIssues": [],
      "updatedAt": "2026-06-17T22:41:02.320Z"
    },
    "banked_cloze-bp-cet4-bk22s3": {
      "rowId": "banked_cloze-bp-cet4-bk22s3",
      "type": "banked_cloze",
      "shapeIssues": [],
      "updatedAt": "2026-06-17T22:41:02.320Z"
    },
    "banked_cloze-bp-cet4-brudvn": {
      "rowId": "banked_cloze-bp-cet4-brudvn",
      "type": "banked_cloze",
      "shapeIssues": [],
      "updatedAt": "2026-06-17T22:41:02.321Z"
    },
    "banked_cloze-bp-cet4-cq61xq": {
      "rowId": "banked_cloze-bp-cet4-cq61xq",
      "type": "banked_cloze",
      "shapeIssues": [],
      "updatedAt": "2026-06-17T22:41:02.322Z"
    },
    "banked_cloze-bp-cet4-d99vsh": {
      "rowId": "banked_cloze-bp-cet4-d99vsh",
      "type": "banked_cloze",
      "shapeIssues": [],
      "updatedAt": "2026-06-17T22:41:02.322Z"
    },
    "banked_cloze-bp-cet4-diyp87": {
      "rowId": "banked_cloze-bp-cet4-diyp87",
      "type": "banked_cloze",
      "shapeIssues": [],
      "updatedAt": "2026-06-17T22:41:02.322Z"
    },
    "banked_cloze-bp-cet4-ef27ke": {
      "rowId": "banked_cloze-bp-cet4-ef27ke",
      "type": "banked_cloze",
      "shapeIssues": [],
      "updatedAt": "2026-06-17T22:41:02.323Z"
    },
    "banked_cloze-bp-cet4-ei6m9d": {
      "rowId": "banked_cloze-bp-cet4-ei6m9d",
      "type": "banked_cloze",
      "shapeIssues": [],
      "updatedAt": "2026-06-17T22:41:02.323Z"
    },
    "banked_cloze-bp-cet4-gm4fch": {
      "rowId": "banked_cloze-bp-cet4-gm4fch",
      "type": "banked_cloze",
      "shapeIssues": [],
      "updatedAt": "2026-06-17T22:41:02.324Z"
    },
    "banked_cloze-bp-cet4-he0pdi": {
      "rowId": "banked_cloze-bp-cet4-he0pdi",
      "type": "banked_cloze",
      "shapeIssues": [],
      "updatedAt": "2026-06-17T22:41:02.324Z"
    },
    "banked_cloze-bp-cet4-iy7m5b": {
      "rowId": "banked_cloze-bp-cet4-iy7m5b",
      "type": "banked_cloze",
      "shapeIssues": [],
      "updatedAt": "2026-06-17T22:41:02.325Z"
    },
    "banked_cloze-bp-cet4-k6owls": {
      "rowId": "banked_cloze-bp-cet4-k6owls",
      "type": "banked_cloze",
      "shapeIssues": [],
      "updatedAt": "2026-06-17T22:41:02.325Z"
    },
    "banked_cloze-bp-cet4-kneb7h": {
      "rowId": "banked_cloze-bp-cet4-kneb7h",
      "type": "banked_cloze",
      "shapeIssues": [],
      "updatedAt": "2026-06-17T22:41:02.326Z"
    },
    "banked_cloze-bp-cet4-nvmqgb": {
      "rowId": "banked_cloze-bp-cet4-nvmqgb",
      "type": "banked_cloze",
      "shapeIssues": [],
      "updatedAt": "2026-06-17T22:41:02.326Z"
    },
    "banked_cloze-bp-cet4-oksdto": {
      "rowId": "banked_cloze-bp-cet4-oksdto",
      "type": "banked_cloze",
      "shapeIssues": [],
      "updatedAt": "2026-06-17T22:41:02.327Z"
    },
    "banked_cloze-bp-cet4-oso7q9": {
      "rowId": "banked_cloze-bp-cet4-oso7q9",
      "type": "banked_cloze",
      "shapeIssues": [],
      "updatedAt": "2026-06-17T22:41:02.327Z"
    },
    "banked_cloze-bp-cet4-s1784g": {
      "rowId": "banked_cloze-bp-cet4-s1784g",
      "type": "banked_cloze",
      "shapeIssues": [],
      "updatedAt": "2026-06-17T22:41:02.327Z"
    },
    "banked_cloze-bp-cet4-s21r4b": {
      "rowId": "banked_cloze-bp-cet4-s21r4b",
      "type": "banked_cloze",
      "shapeIssues": [],
      "updatedAt": "2026-06-17T22:41:02.328Z"
    },
    "banked_cloze-bp-cet4-uf1w02": {
      "rowId": "banked_cloze-bp-cet4-uf1w02",
      "type": "banked_cloze",
      "shapeIssues": [],
      "updatedAt": "2026-06-17T22:41:02.328Z"
    },
    "banked_cloze-bp-cet4-wcckm1": {
      "rowId": "banked_cloze-bp-cet4-wcckm1",
      "type": "banked_cloze",
      "shapeIssues": [],
      "updatedAt": "2026-06-17T22:41:02.329Z"
    },
    "banked_cloze-bp-cet4-wcqozf": {
      "rowId": "banked_cloze-bp-cet4-wcqozf",
      "type": "banked_cloze",
      "shapeIssues": [],
      "updatedAt": "2026-06-17T22:41:02.329Z"
    },
    "banked_cloze-bp-cet4-xwr2s1": {
      "rowId": "banked_cloze-bp-cet4-xwr2s1",
      "type": "banked_cloze",
      "shapeIssues": [],
      "updatedAt": "2026-06-17T22:41:02.329Z"
    },
    "banked_cloze-bp-cet4-ydcsjn": {
      "rowId": "banked_cloze-bp-cet4-ydcsjn",
      "type": "banked_cloze",
      "shapeIssues": [],
      "updatedAt": "2026-06-17T22:41:02.330Z"
    },
    "banked_cloze-bp-cet4-yfytow": {
      "rowId": "banked_cloze-bp-cet4-yfytow",
      "type": "banked_cloze",
      "shapeIssues": [],
      "updatedAt": "2026-06-17T22:41:02.330Z"
    },
    "banked_cloze-bp-cet4-yxhlg9": {
      "rowId": "banked_cloze-bp-cet4-yxhlg9",
      "type": "banked_cloze",
      "shapeIssues": [],
      "updatedAt": "2026-06-17T22:41:02.331Z"
    },
    "banked_cloze-bp-cet4-yzfov2": {
      "rowId": "banked_cloze-bp-cet4-yzfov2",
      "type": "banked_cloze",
      "shapeIssues": [],
      "updatedAt": "2026-06-17T22:41:02.332Z"
    },
    "banked_cloze-bp-cet4-z6cfo": {
      "rowId": "banked_cloze-bp-cet4-z6cfo",
      "type": "banked_cloze",
      "shapeIssues": [],
      "updatedAt": "2026-06-17T22:41:02.332Z"
    },
    "banked_cloze-bp-cet4-zdauyy": {
      "rowId": "banked_cloze-bp-cet4-zdauyy",
      "type": "banked_cloze",
      "shapeIssues": [],
      "updatedAt": "2026-06-17T22:41:02.333Z"
    },
    "banked_cloze-bp-cet4-zoy3qi": {
      "rowId": "banked_cloze-bp-cet4-zoy3qi",
      "type": "banked_cloze",
      "shapeIssues": [],
      "updatedAt": "2026-06-17T22:41:02.333Z"
    },
    "banked_cloze-bp-cet6-108bp4l": {
      "rowId": "banked_cloze-bp-cet6-108bp4l",
      "type": "banked_cloze",
      "shapeIssues": [],
      "updatedAt": "2026-06-17T22:41:02.333Z"
    },
    "banked_cloze-bp-cet6-10kiglz": {
      "rowId": "banked_cloze-bp-cet6-10kiglz",
      "type": "banked_cloze",
      "shapeIssues": [],
      "updatedAt": "2026-06-17T22:41:02.334Z"
    },
    "banked_cloze-bp-cet6-118fkzt": {
      "rowId": "banked_cloze-bp-cet6-118fkzt",
      "type": "banked_cloze",
      "shapeIssues": [],
      "updatedAt": "2026-06-17T22:41:02.334Z"
    },
    "banked_cloze-bp-cet6-11lbg35": {
      "rowId": "banked_cloze-bp-cet6-11lbg35",
      "type": "banked_cloze",
      "shapeIssues": [],
      "updatedAt": "2026-06-17T22:41:02.335Z"
    },
    "banked_cloze-bp-cet6-11x2j1l": {
      "rowId": "banked_cloze-bp-cet6-11x2j1l",
      "type": "banked_cloze",
      "shapeIssues": [],
      "updatedAt": "2026-06-17T22:41:02.335Z"
    },
    "banked_cloze-bp-cet6-14m3r6g": {
      "rowId": "banked_cloze-bp-cet6-14m3r6g",
      "type": "banked_cloze",
      "shapeIssues": [],
      "updatedAt": "2026-06-17T22:41:02.336Z"
    },
    "banked_cloze-bp-cet6-16rw37j": {
      "rowId": "banked_cloze-bp-cet6-16rw37j",
      "type": "banked_cloze",
      "shapeIssues": [],
      "updatedAt": "2026-06-17T22:41:02.337Z"
    },
    "banked_cloze-bp-cet6-16x645e": {
      "rowId": "banked_cloze-bp-cet6-16x645e",
      "type": "banked_cloze",
      "shapeIssues": [],
      "updatedAt": "2026-06-17T22:41:02.337Z"
    },
    "banked_cloze-bp-cet6-16yzuwz": {
      "rowId": "banked_cloze-bp-cet6-16yzuwz",
      "type": "banked_cloze",
      "shapeIssues": [],
      "updatedAt": "2026-06-17T22:41:02.338Z"
    },
    "banked_cloze-bp-cet6-18awx99": {
      "rowId": "banked_cloze-bp-cet6-18awx99",
      "type": "banked_cloze",
      "shapeIssues": [],
      "updatedAt": "2026-06-17T22:41:02.339Z"
    },
    "banked_cloze-bp-cet6-18mqyzg": {
      "rowId": "banked_cloze-bp-cet6-18mqyzg",
      "type": "banked_cloze",
      "shapeIssues": [],
      "updatedAt": "2026-06-17T22:41:02.339Z"
    },
    "banked_cloze-bp-cet6-19chj8a": {
      "rowId": "banked_cloze-bp-cet6-19chj8a",
      "type": "banked_cloze",
      "shapeIssues": [],
      "updatedAt": "2026-06-17T22:41:02.340Z"
    },
    "banked_cloze-bp-cet6-19j1m0u": {
      "rowId": "banked_cloze-bp-cet6-19j1m0u",
      "type": "banked_cloze",
      "shapeIssues": [],
      "updatedAt": "2026-06-17T22:41:02.340Z"
    },
    "banked_cloze-bp-cet6-19jj88z": {
      "rowId": "banked_cloze-bp-cet6-19jj88z",
      "type": "banked_cloze",
      "shapeIssues": [],
      "updatedAt": "2026-06-17T22:41:02.343Z"
    },
    "banked_cloze-bp-cet6-1a088jn": {
      "rowId": "banked_cloze-bp-cet6-1a088jn",
      "type": "banked_cloze",
      "shapeIssues": [],
      "updatedAt": "2026-06-17T22:41:02.344Z"
    },
    "banked_cloze-bp-cet6-1aa25d7": {
      "rowId": "banked_cloze-bp-cet6-1aa25d7",
      "type": "banked_cloze",
      "shapeIssues": [],
      "updatedAt": "2026-06-17T22:41:02.345Z"
    },
    "banked_cloze-bp-cet6-1acum77": {
      "rowId": "banked_cloze-bp-cet6-1acum77",
      "type": "banked_cloze",
      "shapeIssues": [],
      "updatedAt": "2026-06-17T22:41:02.347Z"
    },
    "banked_cloze-bp-cet6-1bw386w": {
      "rowId": "banked_cloze-bp-cet6-1bw386w",
      "type": "banked_cloze",
      "shapeIssues": [],
      "updatedAt": "2026-06-17T22:41:02.348Z"
    },
    "banked_cloze-bp-cet6-1bzxs2i": {
      "rowId": "banked_cloze-bp-cet6-1bzxs2i",
      "type": "banked_cloze",
      "shapeIssues": [],
      "updatedAt": "2026-06-17T22:41:02.349Z"
    },
    "banked_cloze-bp-cet6-1c9o6wg": {
      "rowId": "banked_cloze-bp-cet6-1c9o6wg",
      "type": "banked_cloze",
      "shapeIssues": [],
      "updatedAt": "2026-06-17T22:41:02.350Z"
    },
    "banked_cloze-bp-cet6-1edq5rm": {
      "rowId": "banked_cloze-bp-cet6-1edq5rm",
      "type": "banked_cloze",
      "shapeIssues": [],
      "updatedAt": "2026-06-17T22:41:02.351Z"
    },
    "banked_cloze-bp-cet6-1fh8esr": {
      "rowId": "banked_cloze-bp-cet6-1fh8esr",
      "type": "banked_cloze",
      "shapeIssues": [],
      "updatedAt": "2026-06-17T22:41:02.352Z"
    },
    "banked_cloze-bp-cet6-1fna5j4": {
      "rowId": "banked_cloze-bp-cet6-1fna5j4",
      "type": "banked_cloze",
      "shapeIssues": [],
      "updatedAt": "2026-06-17T22:41:02.353Z"
    },
    "banked_cloze-bp-cet6-1gb7qu": {
      "rowId": "banked_cloze-bp-cet6-1gb7qu",
      "type": "banked_cloze",
      "shapeIssues": [],
      "updatedAt": "2026-06-17T22:41:02.354Z"
    },
    "banked_cloze-bp-cet6-1gk7fr0": {
      "rowId": "banked_cloze-bp-cet6-1gk7fr0",
      "type": "banked_cloze",
      "shapeIssues": [],
      "updatedAt": "2026-06-17T22:41:02.356Z"
    },
    "banked_cloze-bp-cet6-1h2n6cp": {
      "rowId": "banked_cloze-bp-cet6-1h2n6cp",
      "type": "banked_cloze",
      "shapeIssues": [],
      "updatedAt": "2026-06-17T22:41:02.357Z"
    },
    "banked_cloze-bp-cet6-1hzd63o": {
      "rowId": "banked_cloze-bp-cet6-1hzd63o",
      "type": "banked_cloze",
      "shapeIssues": [],
      "updatedAt": "2026-06-17T22:41:02.357Z"
    },
    "banked_cloze-bp-cet6-1i5vqt8": {
      "rowId": "banked_cloze-bp-cet6-1i5vqt8",
      "type": "banked_cloze",
      "shapeIssues": [],
      "updatedAt": "2026-06-17T22:41:02.358Z"
    },
    "banked_cloze-bp-cet6-1ia6hic": {
      "rowId": "banked_cloze-bp-cet6-1ia6hic",
      "type": "banked_cloze",
      "shapeIssues": [],
      "updatedAt": "2026-06-17T22:41:02.358Z"
    },
    "banked_cloze-bp-cet6-1iae7ws": {
      "rowId": "banked_cloze-bp-cet6-1iae7ws",
      "type": "banked_cloze",
      "shapeIssues": [],
      "updatedAt": "2026-06-17T22:41:02.359Z"
    },
    "banked_cloze-bp-cet6-1k7vcub": {
      "rowId": "banked_cloze-bp-cet6-1k7vcub",
      "type": "banked_cloze",
      "shapeIssues": [],
      "updatedAt": "2026-06-17T22:41:02.360Z"
    },
    "banked_cloze-bp-cet6-1kel89f": {
      "rowId": "banked_cloze-bp-cet6-1kel89f",
      "type": "banked_cloze",
      "shapeIssues": [],
      "updatedAt": "2026-06-17T22:41:02.361Z"
    },
    "banked_cloze-bp-cet6-1ktbvfe": {
      "rowId": "banked_cloze-bp-cet6-1ktbvfe",
      "type": "banked_cloze",
      "shapeIssues": [],
      "updatedAt": "2026-06-17T22:41:02.362Z"
    },
    "banked_cloze-bp-cet6-1onn8a8": {
      "rowId": "banked_cloze-bp-cet6-1onn8a8",
      "type": "banked_cloze",
      "shapeIssues": [],
      "updatedAt": "2026-06-17T22:41:02.362Z"
    },
    "banked_cloze-bp-cet6-1p00sbi": {
      "rowId": "banked_cloze-bp-cet6-1p00sbi",
      "type": "banked_cloze",
      "shapeIssues": [],
      "updatedAt": "2026-06-17T22:41:02.363Z"
    },
    "banked_cloze-bp-cet6-1q9a8av": {
      "rowId": "banked_cloze-bp-cet6-1q9a8av",
      "type": "banked_cloze",
      "shapeIssues": [],
      "updatedAt": "2026-06-17T22:41:02.364Z"
    },
    "banked_cloze-bp-cet6-1qxleiq": {
      "rowId": "banked_cloze-bp-cet6-1qxleiq",
      "type": "banked_cloze",
      "shapeIssues": [],
      "updatedAt": "2026-06-17T22:41:02.364Z"
    },
    "banked_cloze-bp-cet6-1slgv6j": {
      "rowId": "banked_cloze-bp-cet6-1slgv6j",
      "type": "banked_cloze",
      "shapeIssues": [],
      "updatedAt": "2026-06-17T22:41:02.365Z"
    },
    "banked_cloze-bp-cet6-1u733e4": {
      "rowId": "banked_cloze-bp-cet6-1u733e4",
      "type": "banked_cloze",
      "shapeIssues": [],
      "updatedAt": "2026-06-17T22:41:02.365Z"
    },
    "banked_cloze-bp-cet6-1udtpyu": {
      "rowId": "banked_cloze-bp-cet6-1udtpyu",
      "type": "banked_cloze",
      "shapeIssues": [],
      "updatedAt": "2026-06-17T22:41:02.366Z"
    },
    "banked_cloze-bp-cet6-1unfd1d": {
      "rowId": "banked_cloze-bp-cet6-1unfd1d",
      "type": "banked_cloze",
      "shapeIssues": [],
      "updatedAt": "2026-06-17T22:41:02.367Z"
    },
    "banked_cloze-bp-cet6-1wkqzl": {
      "rowId": "banked_cloze-bp-cet6-1wkqzl",
      "type": "banked_cloze",
      "shapeIssues": [],
      "updatedAt": "2026-06-17T22:41:02.368Z"
    },
    "banked_cloze-bp-cet6-1wqh3fl": {
      "rowId": "banked_cloze-bp-cet6-1wqh3fl",
      "type": "banked_cloze",
      "shapeIssues": [],
      "updatedAt": "2026-06-17T22:41:02.369Z"
    },
    "banked_cloze-bp-cet6-1xbqb02": {
      "rowId": "banked_cloze-bp-cet6-1xbqb02",
      "type": "banked_cloze",
      "shapeIssues": [],
      "updatedAt": "2026-06-17T22:41:02.370Z"
    },
    "banked_cloze-bp-cet6-1y8sd0j": {
      "rowId": "banked_cloze-bp-cet6-1y8sd0j",
      "type": "banked_cloze",
      "shapeIssues": [],
      "updatedAt": "2026-06-17T22:41:02.371Z"
    },
    "banked_cloze-bp-cet6-1yc3anh": {
      "rowId": "banked_cloze-bp-cet6-1yc3anh",
      "type": "banked_cloze",
      "shapeIssues": [],
      "updatedAt": "2026-06-17T22:41:02.371Z"
    },
    "banked_cloze-bp-cet6-1yy4m3m": {
      "rowId": "banked_cloze-bp-cet6-1yy4m3m",
      "type": "banked_cloze",
      "shapeIssues": [],
      "updatedAt": "2026-06-17T22:41:02.371Z"
    },
    "banked_cloze-bp-cet6-23zgh3": {
      "rowId": "banked_cloze-bp-cet6-23zgh3",
      "type": "banked_cloze",
      "shapeIssues": [],
      "updatedAt": "2026-06-17T22:41:02.372Z"
    },
    "banked_cloze-bp-cet6-2xqqt6": {
      "rowId": "banked_cloze-bp-cet6-2xqqt6",
      "type": "banked_cloze",
      "shapeIssues": [],
      "updatedAt": "2026-06-17T22:41:02.372Z"
    },
    "banked_cloze-bp-cet6-4qft95": {
      "rowId": "banked_cloze-bp-cet6-4qft95",
      "type": "banked_cloze",
      "shapeIssues": [],
      "updatedAt": "2026-06-17T22:41:02.373Z"
    },
    "banked_cloze-bp-cet6-65b30k": {
      "rowId": "banked_cloze-bp-cet6-65b30k",
      "type": "banked_cloze",
      "shapeIssues": [],
      "updatedAt": "2026-06-17T22:41:02.374Z"
    },
    "banked_cloze-bp-cet6-6hsk7x": {
      "rowId": "banked_cloze-bp-cet6-6hsk7x",
      "type": "banked_cloze",
      "shapeIssues": [],
      "updatedAt": "2026-06-17T22:41:02.374Z"
    },
    "banked_cloze-bp-cet6-6p6g4l": {
      "rowId": "banked_cloze-bp-cet6-6p6g4l",
      "type": "banked_cloze",
      "shapeIssues": [],
      "updatedAt": "2026-06-17T22:41:02.375Z"
    },
    "banked_cloze-bp-cet6-7otvze": {
      "rowId": "banked_cloze-bp-cet6-7otvze",
      "type": "banked_cloze",
      "shapeIssues": [],
      "updatedAt": "2026-06-17T22:41:02.375Z"
    },
    "banked_cloze-bp-cet6-89xhb8": {
      "rowId": "banked_cloze-bp-cet6-89xhb8",
      "type": "banked_cloze",
      "shapeIssues": [],
      "updatedAt": "2026-06-17T22:41:02.376Z"
    },
    "banked_cloze-bp-cet6-8tg2yk": {
      "rowId": "banked_cloze-bp-cet6-8tg2yk",
      "type": "banked_cloze",
      "shapeIssues": [],
      "updatedAt": "2026-06-17T22:41:02.376Z"
    },
    "banked_cloze-bp-cet6-9z7lbo": {
      "rowId": "banked_cloze-bp-cet6-9z7lbo",
      "type": "banked_cloze",
      "shapeIssues": [],
      "updatedAt": "2026-06-17T22:41:02.377Z"
    },
    "banked_cloze-bp-cet6-a4ypkj": {
      "rowId": "banked_cloze-bp-cet6-a4ypkj",
      "type": "banked_cloze",
      "shapeIssues": [],
      "updatedAt": "2026-06-17T22:41:02.377Z"
    },
    "banked_cloze-bp-cet6-adc4xt": {
      "rowId": "banked_cloze-bp-cet6-adc4xt",
      "type": "banked_cloze",
      "shapeIssues": [],
      "updatedAt": "2026-06-17T22:41:02.378Z"
    },
    "banked_cloze-bp-cet6-blqr9w": {
      "rowId": "banked_cloze-bp-cet6-blqr9w",
      "type": "banked_cloze",
      "shapeIssues": [],
      "updatedAt": "2026-06-17T22:41:02.378Z"
    },
    "banked_cloze-bp-cet6-bp7o9h": {
      "rowId": "banked_cloze-bp-cet6-bp7o9h",
      "type": "banked_cloze",
      "shapeIssues": [],
      "updatedAt": "2026-06-17T22:41:02.379Z"
    },
    "banked_cloze-bp-cet6-bvpq5p": {
      "rowId": "banked_cloze-bp-cet6-bvpq5p",
      "type": "banked_cloze",
      "shapeIssues": [],
      "updatedAt": "2026-06-17T22:41:02.380Z"
    },
    "banked_cloze-bp-cet6-ccyxdw": {
      "rowId": "banked_cloze-bp-cet6-ccyxdw",
      "type": "banked_cloze",
      "shapeIssues": [],
      "updatedAt": "2026-06-17T22:41:02.380Z"
    },
    "banked_cloze-bp-cet6-ckc5rs": {
      "rowId": "banked_cloze-bp-cet6-ckc5rs",
      "type": "banked_cloze",
      "shapeIssues": [],
      "updatedAt": "2026-06-17T22:41:02.381Z"
    },
    "banked_cloze-bp-cet6-clu056": {
      "rowId": "banked_cloze-bp-cet6-clu056",
      "type": "banked_cloze",
      "shapeIssues": [],
      "updatedAt": "2026-06-17T22:41:02.381Z"
    },
    "banked_cloze-bp-cet6-fdg57b": {
      "rowId": "banked_cloze-bp-cet6-fdg57b",
      "type": "banked_cloze",
      "shapeIssues": [],
      "updatedAt": "2026-06-17T22:41:02.382Z"
    },
    "banked_cloze-bp-cet6-fej240": {
      "rowId": "banked_cloze-bp-cet6-fej240",
      "type": "banked_cloze",
      "shapeIssues": [],
      "updatedAt": "2026-06-17T22:41:02.383Z"
    },
    "banked_cloze-bp-cet6-fhr25c": {
      "rowId": "banked_cloze-bp-cet6-fhr25c",
      "type": "banked_cloze",
      "shapeIssues": [],
      "updatedAt": "2026-06-17T22:41:02.383Z"
    },
    "banked_cloze-bp-cet6-fnzn4h": {
      "rowId": "banked_cloze-bp-cet6-fnzn4h",
      "type": "banked_cloze",
      "shapeIssues": [],
      "updatedAt": "2026-06-17T22:41:02.384Z"
    },
    "banked_cloze-bp-cet6-h3xw34": {
      "rowId": "banked_cloze-bp-cet6-h3xw34",
      "type": "banked_cloze",
      "shapeIssues": [],
      "updatedAt": "2026-06-17T22:41:02.384Z"
    },
    "banked_cloze-bp-cet6-ida7hd": {
      "rowId": "banked_cloze-bp-cet6-ida7hd",
      "type": "banked_cloze",
      "shapeIssues": [],
      "updatedAt": "2026-06-17T22:41:02.385Z"
    },
    "banked_cloze-bp-cet6-ifpsdi": {
      "rowId": "banked_cloze-bp-cet6-ifpsdi",
      "type": "banked_cloze",
      "shapeIssues": [],
      "updatedAt": "2026-06-17T22:41:02.385Z"
    },
    "banked_cloze-bp-cet6-l23fny": {
      "rowId": "banked_cloze-bp-cet6-l23fny",
      "type": "banked_cloze",
      "shapeIssues": [],
      "updatedAt": "2026-06-17T22:41:02.386Z"
    },
    "banked_cloze-bp-cet6-mbcf6n": {
      "rowId": "banked_cloze-bp-cet6-mbcf6n",
      "type": "banked_cloze",
      "shapeIssues": [],
      "updatedAt": "2026-06-17T22:41:02.386Z"
    },
    "banked_cloze-bp-cet6-mcvz40": {
      "rowId": "banked_cloze-bp-cet6-mcvz40",
      "type": "banked_cloze",
      "shapeIssues": [],
      "updatedAt": "2026-06-17T22:41:02.387Z"
    },
    "banked_cloze-bp-cet6-mfg549": {
      "rowId": "banked_cloze-bp-cet6-mfg549",
      "type": "banked_cloze",
      "shapeIssues": [],
      "updatedAt": "2026-06-17T22:41:02.388Z"
    },
    "banked_cloze-bp-cet6-mpkuz0": {
      "rowId": "banked_cloze-bp-cet6-mpkuz0",
      "type": "banked_cloze",
      "shapeIssues": [],
      "updatedAt": "2026-06-17T22:41:02.389Z"
    },
    "banked_cloze-bp-cet6-ng1zcd": {
      "rowId": "banked_cloze-bp-cet6-ng1zcd",
      "type": "banked_cloze",
      "shapeIssues": [],
      "updatedAt": "2026-06-17T22:41:02.389Z"
    },
    "banked_cloze-bp-cet6-nlyxvt": {
      "rowId": "banked_cloze-bp-cet6-nlyxvt",
      "type": "banked_cloze",
      "shapeIssues": [],
      "updatedAt": "2026-06-17T22:41:02.390Z"
    },
    "banked_cloze-bp-cet6-nwrllj": {
      "rowId": "banked_cloze-bp-cet6-nwrllj",
      "type": "banked_cloze",
      "shapeIssues": [],
      "updatedAt": "2026-06-17T22:41:02.390Z"
    },
    "banked_cloze-bp-cet6-oj0k7s": {
      "rowId": "banked_cloze-bp-cet6-oj0k7s",
      "type": "banked_cloze",
      "shapeIssues": [],
      "updatedAt": "2026-06-17T22:41:02.391Z"
    },
    "banked_cloze-bp-cet6-pzanzn": {
      "rowId": "banked_cloze-bp-cet6-pzanzn",
      "type": "banked_cloze",
      "shapeIssues": [],
      "updatedAt": "2026-06-17T22:41:02.392Z"
    },
    "banked_cloze-bp-cet6-q5gden": {
      "rowId": "banked_cloze-bp-cet6-q5gden",
      "type": "banked_cloze",
      "shapeIssues": [],
      "updatedAt": "2026-06-17T22:41:02.393Z"
    },
    "banked_cloze-bp-cet6-qnbtzc": {
      "rowId": "banked_cloze-bp-cet6-qnbtzc",
      "type": "banked_cloze",
      "shapeIssues": [],
      "updatedAt": "2026-06-17T22:41:02.393Z"
    },
    "banked_cloze-bp-cet6-qpyl0u": {
      "rowId": "banked_cloze-bp-cet6-qpyl0u",
      "type": "banked_cloze",
      "shapeIssues": [],
      "updatedAt": "2026-06-17T22:41:02.394Z"
    },
    "banked_cloze-bp-cet6-r9dy11": {
      "rowId": "banked_cloze-bp-cet6-r9dy11",
      "type": "banked_cloze",
      "shapeIssues": [],
      "updatedAt": "2026-06-17T22:41:02.394Z"
    },
    "banked_cloze-bp-cet6-slldok": {
      "rowId": "banked_cloze-bp-cet6-slldok",
      "type": "banked_cloze",
      "shapeIssues": [],
      "updatedAt": "2026-06-17T22:41:02.395Z"
    },
    "banked_cloze-bp-cet6-tzfiz2": {
      "rowId": "banked_cloze-bp-cet6-tzfiz2",
      "type": "banked_cloze",
      "shapeIssues": [],
      "updatedAt": "2026-06-17T22:41:02.395Z"
    },
    "banked_cloze-bp-cet6-uuppva": {
      "rowId": "banked_cloze-bp-cet6-uuppva",
      "type": "banked_cloze",
      "shapeIssues": [],
      "updatedAt": "2026-06-17T22:41:02.396Z"
    },
    "banked_cloze-bp-cet6-vlkuvw": {
      "rowId": "banked_cloze-bp-cet6-vlkuvw",
      "type": "banked_cloze",
      "shapeIssues": [],
      "updatedAt": "2026-06-17T22:41:02.396Z"
    },
    "banked_cloze-bp-cet6-w96hla": {
      "rowId": "banked_cloze-bp-cet6-w96hla",
      "type": "banked_cloze",
      "shapeIssues": [],
      "updatedAt": "2026-06-17T22:41:02.397Z"
    },
    "banked_cloze-bp-cet6-watgbm": {
      "rowId": "banked_cloze-bp-cet6-watgbm",
      "type": "banked_cloze",
      "shapeIssues": [],
      "updatedAt": "2026-06-17T22:41:02.398Z"
    },
    "banked_cloze-bp-cet6-x1eecl": {
      "rowId": "banked_cloze-bp-cet6-x1eecl",
      "type": "banked_cloze",
      "shapeIssues": [],
      "updatedAt": "2026-06-17T22:41:02.398Z"
    },
    "banked_cloze-bp-cet6-x4c3ad": {
      "rowId": "banked_cloze-bp-cet6-x4c3ad",
      "type": "banked_cloze",
      "shapeIssues": [],
      "updatedAt": "2026-06-17T22:41:02.399Z"
    },
    "banked_cloze-bp-cet6-ybzmg3": {
      "rowId": "banked_cloze-bp-cet6-ybzmg3",
      "type": "banked_cloze",
      "shapeIssues": [],
      "updatedAt": "2026-06-17T22:41:02.400Z"
    },
    "banked_cloze-bp-cet6-z0a0bk": {
      "rowId": "banked_cloze-bp-cet6-z0a0bk",
      "type": "banked_cloze",
      "shapeIssues": [],
      "updatedAt": "2026-06-17T22:41:02.400Z"
    },
    "banked_cloze-bp-cet6-zjfwtq": {
      "rowId": "banked_cloze-bp-cet6-zjfwtq",
      "type": "banked_cloze",
      "shapeIssues": [],
      "updatedAt": "2026-06-17T22:41:02.402Z"
    },
    "banked_cloze-bp-cet6-zx5dqy": {
      "rowId": "banked_cloze-bp-cet6-zx5dqy",
      "type": "banked_cloze",
      "shapeIssues": [],
      "updatedAt": "2026-06-17T22:41:02.402Z"
    },
    "seven_select-sp-kaoyan-10pripf": {
      "rowId": "seven_select-sp-kaoyan-10pripf",
      "type": "seven_select",
      "shapeIssues": [],
      "updatedAt": "2026-06-17T22:41:02.402Z"
    },
    "seven_select-sp-kaoyan-11hlxy": {
      "rowId": "seven_select-sp-kaoyan-11hlxy",
      "type": "seven_select",
      "shapeIssues": [],
      "updatedAt": "2026-06-17T22:41:02.403Z"
    },
    "seven_select-sp-kaoyan-1242wky": {
      "rowId": "seven_select-sp-kaoyan-1242wky",
      "type": "seven_select",
      "shapeIssues": [],
      "updatedAt": "2026-06-17T22:41:02.404Z"
    },
    "seven_select-sp-kaoyan-12ok6bx": {
      "rowId": "seven_select-sp-kaoyan-12ok6bx",
      "type": "seven_select",
      "shapeIssues": [],
      "updatedAt": "2026-06-17T22:41:02.404Z"
    },
    "seven_select-sp-kaoyan-12resji": {
      "rowId": "seven_select-sp-kaoyan-12resji",
      "type": "seven_select",
      "shapeIssues": [],
      "updatedAt": "2026-06-17T22:41:02.405Z"
    },
    "seven_select-sp-kaoyan-1359edp": {
      "rowId": "seven_select-sp-kaoyan-1359edp",
      "type": "seven_select",
      "shapeIssues": [],
      "updatedAt": "2026-06-17T22:41:02.405Z"
    },
    "seven_select-sp-kaoyan-140fq0d": {
      "rowId": "seven_select-sp-kaoyan-140fq0d",
      "type": "seven_select",
      "shapeIssues": [],
      "updatedAt": "2026-06-17T22:41:02.406Z"
    },
    "seven_select-sp-kaoyan-14ycrts": {
      "rowId": "seven_select-sp-kaoyan-14ycrts",
      "type": "seven_select",
      "shapeIssues": [],
      "updatedAt": "2026-06-17T22:41:02.406Z"
    },
    "seven_select-sp-kaoyan-15228fj": {
      "rowId": "seven_select-sp-kaoyan-15228fj",
      "type": "seven_select",
      "shapeIssues": [],
      "updatedAt": "2026-06-17T22:41:02.407Z"
    },
    "seven_select-sp-kaoyan-15cnifh": {
      "rowId": "seven_select-sp-kaoyan-15cnifh",
      "type": "seven_select",
      "shapeIssues": [],
      "updatedAt": "2026-06-17T22:41:02.407Z"
    },
    "seven_select-sp-kaoyan-16lpfwj": {
      "rowId": "seven_select-sp-kaoyan-16lpfwj",
      "type": "seven_select",
      "shapeIssues": [],
      "updatedAt": "2026-06-17T22:41:02.408Z"
    },
    "seven_select-sp-kaoyan-16ovz93": {
      "rowId": "seven_select-sp-kaoyan-16ovz93",
      "type": "seven_select",
      "shapeIssues": [],
      "updatedAt": "2026-06-17T22:41:02.408Z"
    },
    "seven_select-sp-kaoyan-1ccok0g": {
      "rowId": "seven_select-sp-kaoyan-1ccok0g",
      "type": "seven_select",
      "shapeIssues": [],
      "updatedAt": "2026-06-17T22:41:02.409Z"
    },
    "seven_select-sp-kaoyan-1d0p0u0": {
      "rowId": "seven_select-sp-kaoyan-1d0p0u0",
      "type": "seven_select",
      "shapeIssues": [],
      "updatedAt": "2026-06-17T22:41:02.409Z"
    },
    "seven_select-sp-kaoyan-1g7t7pb": {
      "rowId": "seven_select-sp-kaoyan-1g7t7pb",
      "type": "seven_select",
      "shapeIssues": [],
      "updatedAt": "2026-06-17T22:41:02.410Z"
    },
    "seven_select-sp-kaoyan-1jvydjm": {
      "rowId": "seven_select-sp-kaoyan-1jvydjm",
      "type": "seven_select",
      "shapeIssues": [],
      "updatedAt": "2026-06-17T22:41:02.410Z"
    },
    "seven_select-sp-kaoyan-1q5l2ko": {
      "rowId": "seven_select-sp-kaoyan-1q5l2ko",
      "type": "seven_select",
      "shapeIssues": [],
      "updatedAt": "2026-06-17T22:41:02.411Z"
    },
    "seven_select-sp-kaoyan-1s5nn4e": {
      "rowId": "seven_select-sp-kaoyan-1s5nn4e",
      "type": "seven_select",
      "shapeIssues": [],
      "updatedAt": "2026-06-17T22:41:02.411Z"
    },
    "seven_select-sp-kaoyan-1sgdtxt": {
      "rowId": "seven_select-sp-kaoyan-1sgdtxt",
      "type": "seven_select",
      "shapeIssues": [],
      "updatedAt": "2026-06-17T22:41:02.412Z"
    },
    "seven_select-sp-kaoyan-1smab29": {
      "rowId": "seven_select-sp-kaoyan-1smab29",
      "type": "seven_select",
      "shapeIssues": [],
      "updatedAt": "2026-06-17T22:41:02.412Z"
    },
    "seven_select-sp-kaoyan-1v3cjbt": {
      "rowId": "seven_select-sp-kaoyan-1v3cjbt",
      "type": "seven_select",
      "shapeIssues": [],
      "updatedAt": "2026-06-17T22:41:02.413Z"
    },
    "seven_select-sp-kaoyan-1wuspab": {
      "rowId": "seven_select-sp-kaoyan-1wuspab",
      "type": "seven_select",
      "shapeIssues": [],
      "updatedAt": "2026-06-17T22:41:02.413Z"
    },
    "seven_select-sp-kaoyan-28w8l3": {
      "rowId": "seven_select-sp-kaoyan-28w8l3",
      "type": "seven_select",
      "shapeIssues": [],
      "updatedAt": "2026-06-17T22:41:02.414Z"
    },
    "seven_select-sp-kaoyan-392i5x": {
      "rowId": "seven_select-sp-kaoyan-392i5x",
      "type": "seven_select",
      "shapeIssues": [],
      "updatedAt": "2026-06-17T22:41:02.414Z"
    },
    "seven_select-sp-kaoyan-3a2enx": {
      "rowId": "seven_select-sp-kaoyan-3a2enx",
      "type": "seven_select",
      "shapeIssues": [],
      "updatedAt": "2026-06-17T22:41:02.415Z"
    },
    "seven_select-sp-kaoyan-743rx2": {
      "rowId": "seven_select-sp-kaoyan-743rx2",
      "type": "seven_select",
      "shapeIssues": [],
      "updatedAt": "2026-06-17T22:41:02.416Z"
    },
    "seven_select-sp-kaoyan-770u5n": {
      "rowId": "seven_select-sp-kaoyan-770u5n",
      "type": "seven_select",
      "shapeIssues": [],
      "updatedAt": "2026-06-17T22:41:02.416Z"
    },
    "seven_select-sp-kaoyan-8tw2je": {
      "rowId": "seven_select-sp-kaoyan-8tw2je",
      "type": "seven_select",
      "shapeIssues": [],
      "updatedAt": "2026-06-17T22:41:02.417Z"
    },
    "seven_select-sp-kaoyan-9ljwik": {
      "rowId": "seven_select-sp-kaoyan-9ljwik",
      "type": "seven_select",
      "shapeIssues": [],
      "updatedAt": "2026-06-17T22:41:02.417Z"
    },
    "seven_select-sp-kaoyan-bbi9u9": {
      "rowId": "seven_select-sp-kaoyan-bbi9u9",
      "type": "seven_select",
      "shapeIssues": [],
      "updatedAt": "2026-06-17T22:41:02.418Z"
    },
    "seven_select-sp-kaoyan-bivw91": {
      "rowId": "seven_select-sp-kaoyan-bivw91",
      "type": "seven_select",
      "shapeIssues": [],
      "updatedAt": "2026-06-17T22:41:02.418Z"
    },
    "seven_select-sp-kaoyan-c8eqw9": {
      "rowId": "seven_select-sp-kaoyan-c8eqw9",
      "type": "seven_select",
      "shapeIssues": [],
      "updatedAt": "2026-06-17T22:41:02.419Z"
    },
    "seven_select-sp-kaoyan-cjr8pq": {
      "rowId": "seven_select-sp-kaoyan-cjr8pq",
      "type": "seven_select",
      "shapeIssues": [],
      "updatedAt": "2026-06-17T22:41:02.419Z"
    },
    "seven_select-sp-kaoyan-do9zhs": {
      "rowId": "seven_select-sp-kaoyan-do9zhs",
      "type": "seven_select",
      "shapeIssues": [],
      "updatedAt": "2026-06-17T22:41:02.420Z"
    },
    "seven_select-sp-kaoyan-e6jo16": {
      "rowId": "seven_select-sp-kaoyan-e6jo16",
      "type": "seven_select",
      "shapeIssues": [],
      "updatedAt": "2026-06-17T22:41:02.420Z"
    },
    "seven_select-sp-kaoyan-j0cz9u": {
      "rowId": "seven_select-sp-kaoyan-j0cz9u",
      "type": "seven_select",
      "shapeIssues": [],
      "updatedAt": "2026-06-17T22:41:02.421Z"
    },
    "seven_select-sp-kaoyan-jjbjy6": {
      "rowId": "seven_select-sp-kaoyan-jjbjy6",
      "type": "seven_select",
      "shapeIssues": [],
      "updatedAt": "2026-06-17T22:41:02.421Z"
    },
    "seven_select-sp-kaoyan-jk9ihc": {
      "rowId": "seven_select-sp-kaoyan-jk9ihc",
      "type": "seven_select",
      "shapeIssues": [],
      "updatedAt": "2026-06-17T22:41:02.422Z"
    },
    "seven_select-sp-kaoyan-jw8r7l": {
      "rowId": "seven_select-sp-kaoyan-jw8r7l",
      "type": "seven_select",
      "shapeIssues": [],
      "updatedAt": "2026-06-17T22:41:02.422Z"
    },
    "seven_select-sp-kaoyan-k0xshl": {
      "rowId": "seven_select-sp-kaoyan-k0xshl",
      "type": "seven_select",
      "shapeIssues": [],
      "updatedAt": "2026-06-17T22:41:02.423Z"
    },
    "seven_select-sp-kaoyan-mhfg7y": {
      "rowId": "seven_select-sp-kaoyan-mhfg7y",
      "type": "seven_select",
      "shapeIssues": [],
      "updatedAt": "2026-06-17T22:41:02.423Z"
    },
    "seven_select-sp-kaoyan-n4xy6": {
      "rowId": "seven_select-sp-kaoyan-n4xy6",
      "type": "seven_select",
      "shapeIssues": [],
      "updatedAt": "2026-06-17T22:41:02.424Z"
    },
    "seven_select-sp-kaoyan-nlubp3": {
      "rowId": "seven_select-sp-kaoyan-nlubp3",
      "type": "seven_select",
      "shapeIssues": [],
      "updatedAt": "2026-06-17T22:41:02.424Z"
    },
    "seven_select-sp-kaoyan-octc2g": {
      "rowId": "seven_select-sp-kaoyan-octc2g",
      "type": "seven_select",
      "shapeIssues": [],
      "updatedAt": "2026-06-17T22:41:02.425Z"
    },
    "seven_select-sp-kaoyan-oe2ydw": {
      "rowId": "seven_select-sp-kaoyan-oe2ydw",
      "type": "seven_select",
      "shapeIssues": [],
      "updatedAt": "2026-06-17T22:41:02.426Z"
    },
    "seven_select-sp-kaoyan-peak5j": {
      "rowId": "seven_select-sp-kaoyan-peak5j",
      "type": "seven_select",
      "shapeIssues": [],
      "updatedAt": "2026-06-17T22:41:02.426Z"
    },
    "seven_select-sp-kaoyan-phlbfm": {
      "rowId": "seven_select-sp-kaoyan-phlbfm",
      "type": "seven_select",
      "shapeIssues": [],
      "updatedAt": "2026-06-17T22:41:02.427Z"
    },
    "seven_select-sp-kaoyan-putlmb": {
      "rowId": "seven_select-sp-kaoyan-putlmb",
      "type": "seven_select",
      "shapeIssues": [],
      "updatedAt": "2026-06-17T22:41:02.427Z"
    },
    "seven_select-sp-kaoyan-pxvtb5": {
      "rowId": "seven_select-sp-kaoyan-pxvtb5",
      "type": "seven_select",
      "shapeIssues": [],
      "updatedAt": "2026-06-17T22:41:02.428Z"
    },
    "seven_select-sp-kaoyan-q6ccfg": {
      "rowId": "seven_select-sp-kaoyan-q6ccfg",
      "type": "seven_select",
      "shapeIssues": [],
      "updatedAt": "2026-06-17T22:41:02.429Z"
    },
    "seven_select-sp-kaoyan-ry5zyv": {
      "rowId": "seven_select-sp-kaoyan-ry5zyv",
      "type": "seven_select",
      "shapeIssues": [],
      "updatedAt": "2026-06-17T22:41:02.430Z"
    },
    "seven_select-sp-kaoyan-tk7afb": {
      "rowId": "seven_select-sp-kaoyan-tk7afb",
      "type": "seven_select",
      "shapeIssues": [],
      "updatedAt": "2026-06-17T22:41:02.430Z"
    },
    "seven_select-sp-kaoyan-uref0z": {
      "rowId": "seven_select-sp-kaoyan-uref0z",
      "type": "seven_select",
      "shapeIssues": [],
      "updatedAt": "2026-06-17T22:41:02.431Z"
    },
    "seven_select-sp-kaoyan-wtgca9": {
      "rowId": "seven_select-sp-kaoyan-wtgca9",
      "type": "seven_select",
      "shapeIssues": [],
      "updatedAt": "2026-06-17T22:41:02.431Z"
    },
    "seven_select-sp-中考-11qrvvh": {
      "rowId": "seven_select-sp-中考-11qrvvh",
      "type": "seven_select",
      "shapeIssues": [],
      "updatedAt": "2026-06-17T22:41:02.432Z"
    },
    "seven_select-sp-中考-13o96e6": {
      "rowId": "seven_select-sp-中考-13o96e6",
      "type": "seven_select",
      "shapeIssues": [],
      "updatedAt": "2026-06-17T22:41:02.432Z"
    },
    "seven_select-sp-中考-16qs3iz": {
      "rowId": "seven_select-sp-中考-16qs3iz",
      "type": "seven_select",
      "shapeIssues": [],
      "updatedAt": "2026-06-17T22:41:02.433Z"
    },
    "seven_select-sp-中考-196no92": {
      "rowId": "seven_select-sp-中考-196no92",
      "type": "seven_select",
      "shapeIssues": [],
      "updatedAt": "2026-06-17T22:41:02.434Z"
    },
    "seven_select-sp-中考-1aqvfm7": {
      "rowId": "seven_select-sp-中考-1aqvfm7",
      "type": "seven_select",
      "shapeIssues": [],
      "updatedAt": "2026-06-17T22:41:02.434Z"
    },
    "seven_select-sp-中考-1dyeqkk": {
      "rowId": "seven_select-sp-中考-1dyeqkk",
      "type": "seven_select",
      "shapeIssues": [],
      "updatedAt": "2026-06-17T22:41:02.435Z"
    },
    "seven_select-sp-中考-1fpotsy": {
      "rowId": "seven_select-sp-中考-1fpotsy",
      "type": "seven_select",
      "shapeIssues": [],
      "updatedAt": "2026-06-17T22:41:02.436Z"
    },
    "seven_select-sp-中考-1gl1apa": {
      "rowId": "seven_select-sp-中考-1gl1apa",
      "type": "seven_select",
      "shapeIssues": [],
      "updatedAt": "2026-06-17T22:41:02.436Z"
    },
    "seven_select-sp-中考-1h4akkd": {
      "rowId": "seven_select-sp-中考-1h4akkd",
      "type": "seven_select",
      "shapeIssues": [],
      "updatedAt": "2026-06-17T22:41:02.437Z"
    },
    "seven_select-sp-中考-1i85gx6": {
      "rowId": "seven_select-sp-中考-1i85gx6",
      "type": "seven_select",
      "shapeIssues": [],
      "updatedAt": "2026-06-17T22:41:02.437Z"
    },
    "seven_select-sp-中考-1ilajss": {
      "rowId": "seven_select-sp-中考-1ilajss",
      "type": "seven_select",
      "shapeIssues": [],
      "updatedAt": "2026-06-17T22:41:02.438Z"
    },
    "seven_select-sp-中考-1j13zkl": {
      "rowId": "seven_select-sp-中考-1j13zkl",
      "type": "seven_select",
      "shapeIssues": [],
      "updatedAt": "2026-06-17T22:41:02.439Z"
    },
    "seven_select-sp-中考-1j9u6fk": {
      "rowId": "seven_select-sp-中考-1j9u6fk",
      "type": "seven_select",
      "shapeIssues": [],
      "updatedAt": "2026-06-17T22:41:02.439Z"
    },
    "seven_select-sp-中考-1k33fw": {
      "rowId": "seven_select-sp-中考-1k33fw",
      "type": "seven_select",
      "shapeIssues": [],
      "updatedAt": "2026-06-17T22:41:02.440Z"
    },
    "seven_select-sp-中考-1k688xk": {
      "rowId": "seven_select-sp-中考-1k688xk",
      "type": "seven_select",
      "shapeIssues": [],
      "updatedAt": "2026-06-17T22:41:02.440Z"
    },
    "seven_select-sp-中考-1mkn0di": {
      "rowId": "seven_select-sp-中考-1mkn0di",
      "type": "seven_select",
      "shapeIssues": [],
      "updatedAt": "2026-06-17T22:41:02.441Z"
    },
    "seven_select-sp-中考-1njadjm": {
      "rowId": "seven_select-sp-中考-1njadjm",
      "type": "seven_select",
      "shapeIssues": [],
      "updatedAt": "2026-06-17T22:41:02.442Z"
    },
    "seven_select-sp-中考-1qw9c26": {
      "rowId": "seven_select-sp-中考-1qw9c26",
      "type": "seven_select",
      "shapeIssues": [],
      "updatedAt": "2026-06-17T22:41:02.442Z"
    },
    "seven_select-sp-中考-1re2r1f": {
      "rowId": "seven_select-sp-中考-1re2r1f",
      "type": "seven_select",
      "shapeIssues": [],
      "updatedAt": "2026-06-17T22:41:02.443Z"
    },
    "seven_select-sp-中考-1rk43h0": {
      "rowId": "seven_select-sp-中考-1rk43h0",
      "type": "seven_select",
      "shapeIssues": [],
      "updatedAt": "2026-06-17T22:41:02.443Z"
    },
    "seven_select-sp-中考-1s7mzdm": {
      "rowId": "seven_select-sp-中考-1s7mzdm",
      "type": "seven_select",
      "shapeIssues": [],
      "updatedAt": "2026-06-17T22:41:02.445Z"
    },
    "seven_select-sp-中考-1tcr1jh": {
      "rowId": "seven_select-sp-中考-1tcr1jh",
      "type": "seven_select",
      "shapeIssues": [],
      "updatedAt": "2026-06-17T22:41:02.445Z"
    },
    "seven_select-sp-中考-1u5s6r9": {
      "rowId": "seven_select-sp-中考-1u5s6r9",
      "type": "seven_select",
      "shapeIssues": [],
      "updatedAt": "2026-06-17T22:41:02.446Z"
    },
    "seven_select-sp-中考-1v3zxmj": {
      "rowId": "seven_select-sp-中考-1v3zxmj",
      "type": "seven_select",
      "shapeIssues": [],
      "updatedAt": "2026-06-17T22:41:02.447Z"
    },
    "seven_select-sp-中考-1v79jio": {
      "rowId": "seven_select-sp-中考-1v79jio",
      "type": "seven_select",
      "shapeIssues": [],
      "updatedAt": "2026-06-17T22:41:02.448Z"
    },
    "seven_select-sp-中考-31ziah": {
      "rowId": "seven_select-sp-中考-31ziah",
      "type": "seven_select",
      "shapeIssues": [],
      "updatedAt": "2026-06-17T22:41:02.448Z"
    },
    "seven_select-sp-中考-4j34ai": {
      "rowId": "seven_select-sp-中考-4j34ai",
      "type": "seven_select",
      "shapeIssues": [],
      "updatedAt": "2026-06-17T22:41:02.449Z"
    },
    "seven_select-sp-中考-6li36c": {
      "rowId": "seven_select-sp-中考-6li36c",
      "type": "seven_select",
      "shapeIssues": [],
      "updatedAt": "2026-06-17T22:41:02.450Z"
    },
    "seven_select-sp-中考-8pqqfx": {
      "rowId": "seven_select-sp-中考-8pqqfx",
      "type": "seven_select",
      "shapeIssues": [],
      "updatedAt": "2026-06-17T22:41:02.451Z"
    },
    "seven_select-sp-中考-9e03i3": {
      "rowId": "seven_select-sp-中考-9e03i3",
      "type": "seven_select",
      "shapeIssues": [],
      "updatedAt": "2026-06-17T22:41:02.453Z"
    },
    "seven_select-sp-中考-cxsdg": {
      "rowId": "seven_select-sp-中考-cxsdg",
      "type": "seven_select",
      "shapeIssues": [],
      "updatedAt": "2026-06-17T22:41:02.454Z"
    },
    "seven_select-sp-中考-ejp7mh": {
      "rowId": "seven_select-sp-中考-ejp7mh",
      "type": "seven_select",
      "shapeIssues": [],
      "updatedAt": "2026-06-17T22:41:02.454Z"
    },
    "seven_select-sp-中考-fhbsuq": {
      "rowId": "seven_select-sp-中考-fhbsuq",
      "type": "seven_select",
      "shapeIssues": [],
      "updatedAt": "2026-06-17T22:41:02.455Z"
    },
    "seven_select-sp-中考-l6li5w": {
      "rowId": "seven_select-sp-中考-l6li5w",
      "type": "seven_select",
      "shapeIssues": [],
      "updatedAt": "2026-06-17T22:41:02.455Z"
    },
    "seven_select-sp-中考-lev21n": {
      "rowId": "seven_select-sp-中考-lev21n",
      "type": "seven_select",
      "shapeIssues": [],
      "updatedAt": "2026-06-17T22:41:02.456Z"
    },
    "seven_select-sp-中考-lhfmwp": {
      "rowId": "seven_select-sp-中考-lhfmwp",
      "type": "seven_select",
      "shapeIssues": [],
      "updatedAt": "2026-06-17T22:41:02.456Z"
    },
    "seven_select-sp-中考-n2mxo0": {
      "rowId": "seven_select-sp-中考-n2mxo0",
      "type": "seven_select",
      "shapeIssues": [],
      "updatedAt": "2026-06-17T22:41:02.457Z"
    },
    "seven_select-sp-中考-nocq94": {
      "rowId": "seven_select-sp-中考-nocq94",
      "type": "seven_select",
      "shapeIssues": [],
      "updatedAt": "2026-06-17T22:41:02.458Z"
    },
    "seven_select-sp-中考-pi2ool": {
      "rowId": "seven_select-sp-中考-pi2ool",
      "type": "seven_select",
      "shapeIssues": [],
      "updatedAt": "2026-06-17T22:41:02.459Z"
    },
    "seven_select-sp-中考-pj5dys": {
      "rowId": "seven_select-sp-中考-pj5dys",
      "type": "seven_select",
      "shapeIssues": [],
      "updatedAt": "2026-06-17T22:41:02.459Z"
    },
    "seven_select-sp-中考-rfpdbb": {
      "rowId": "seven_select-sp-中考-rfpdbb",
      "type": "seven_select",
      "shapeIssues": [],
      "updatedAt": "2026-06-17T22:41:02.460Z"
    },
    "seven_select-sp-中考-rxe4wq": {
      "rowId": "seven_select-sp-中考-rxe4wq",
      "type": "seven_select",
      "shapeIssues": [],
      "updatedAt": "2026-06-17T22:41:02.461Z"
    },
    "seven_select-sp-中考-t4d7bv": {
      "rowId": "seven_select-sp-中考-t4d7bv",
      "type": "seven_select",
      "shapeIssues": [],
      "updatedAt": "2026-06-17T22:41:02.462Z"
    },
    "seven_select-sp-中考-upzrz0": {
      "rowId": "seven_select-sp-中考-upzrz0",
      "type": "seven_select",
      "shapeIssues": [],
      "updatedAt": "2026-06-17T22:41:02.462Z"
    },
    "seven_select-sp-中考-w4kgi": {
      "rowId": "seven_select-sp-中考-w4kgi",
      "type": "seven_select",
      "shapeIssues": [],
      "updatedAt": "2026-06-17T22:41:02.463Z"
    },
    "seven_select-sp-中考-wakawn": {
      "rowId": "seven_select-sp-中考-wakawn",
      "type": "seven_select",
      "shapeIssues": [],
      "updatedAt": "2026-06-17T22:41:02.464Z"
    },
    "seven_select-sp-中考-yfphqe": {
      "rowId": "seven_select-sp-中考-yfphqe",
      "type": "seven_select",
      "shapeIssues": [],
      "updatedAt": "2026-06-17T22:41:02.464Z"
    },
    "seven_select-sp-高考-12ip10v": {
      "rowId": "seven_select-sp-高考-12ip10v",
      "type": "seven_select",
      "shapeIssues": [],
      "updatedAt": "2026-06-17T22:41:02.465Z"
    },
    "seven_select-sp-高考-1318vtw": {
      "rowId": "seven_select-sp-高考-1318vtw",
      "type": "seven_select",
      "shapeIssues": [],
      "updatedAt": "2026-06-17T22:41:02.465Z"
    },
    "seven_select-sp-高考-16ap3kn": {
      "rowId": "seven_select-sp-高考-16ap3kn",
      "type": "seven_select",
      "shapeIssues": [],
      "updatedAt": "2026-06-17T22:41:02.466Z"
    },
    "seven_select-sp-高考-16i763g": {
      "rowId": "seven_select-sp-高考-16i763g",
      "type": "seven_select",
      "shapeIssues": [],
      "updatedAt": "2026-06-17T22:41:02.467Z"
    },
    "seven_select-sp-高考-17sqv1j": {
      "rowId": "seven_select-sp-高考-17sqv1j",
      "type": "seven_select",
      "shapeIssues": [],
      "updatedAt": "2026-06-17T22:41:02.467Z"
    },
    "seven_select-sp-高考-17x4bnn": {
      "rowId": "seven_select-sp-高考-17x4bnn",
      "type": "seven_select",
      "shapeIssues": [],
      "updatedAt": "2026-06-17T22:41:02.468Z"
    },
    "seven_select-sp-高考-185h90p": {
      "rowId": "seven_select-sp-高考-185h90p",
      "type": "seven_select",
      "shapeIssues": [],
      "updatedAt": "2026-06-17T22:41:02.468Z"
    },
    "seven_select-sp-高考-1b8cfum": {
      "rowId": "seven_select-sp-高考-1b8cfum",
      "type": "seven_select",
      "shapeIssues": [],
      "updatedAt": "2026-06-17T22:41:02.469Z"
    },
    "seven_select-sp-高考-1cj6zyk": {
      "rowId": "seven_select-sp-高考-1cj6zyk",
      "type": "seven_select",
      "shapeIssues": [],
      "updatedAt": "2026-06-17T22:41:02.470Z"
    },
    "seven_select-sp-高考-1f6ajg9": {
      "rowId": "seven_select-sp-高考-1f6ajg9",
      "type": "seven_select",
      "shapeIssues": [],
      "updatedAt": "2026-06-17T22:41:02.470Z"
    },
    "seven_select-sp-高考-1fo29fh": {
      "rowId": "seven_select-sp-高考-1fo29fh",
      "type": "seven_select",
      "shapeIssues": [],
      "updatedAt": "2026-06-17T22:41:02.471Z"
    },
    "seven_select-sp-高考-1gxrgid": {
      "rowId": "seven_select-sp-高考-1gxrgid",
      "type": "seven_select",
      "shapeIssues": [],
      "updatedAt": "2026-06-17T22:41:02.471Z"
    },
    "seven_select-sp-高考-1lcoh8q": {
      "rowId": "seven_select-sp-高考-1lcoh8q",
      "type": "seven_select",
      "shapeIssues": [],
      "updatedAt": "2026-06-17T22:41:02.472Z"
    },
    "seven_select-sp-高考-1m3mppk": {
      "rowId": "seven_select-sp-高考-1m3mppk",
      "type": "seven_select",
      "shapeIssues": [],
      "updatedAt": "2026-06-17T22:41:02.473Z"
    },
    "seven_select-sp-高考-1m9cvsp": {
      "rowId": "seven_select-sp-高考-1m9cvsp",
      "type": "seven_select",
      "shapeIssues": [],
      "updatedAt": "2026-06-17T22:41:02.473Z"
    },
    "seven_select-sp-高考-1mrvra4": {
      "rowId": "seven_select-sp-高考-1mrvra4",
      "type": "seven_select",
      "shapeIssues": [],
      "updatedAt": "2026-06-17T22:41:02.474Z"
    },
    "seven_select-sp-高考-1nr5l5f": {
      "rowId": "seven_select-sp-高考-1nr5l5f",
      "type": "seven_select",
      "shapeIssues": [],
      "updatedAt": "2026-06-17T22:41:02.475Z"
    },
    "seven_select-sp-高考-1o8x48f": {
      "rowId": "seven_select-sp-高考-1o8x48f",
      "type": "seven_select",
      "shapeIssues": [],
      "updatedAt": "2026-06-17T22:41:02.475Z"
    },
    "seven_select-sp-高考-1qv8tlb": {
      "rowId": "seven_select-sp-高考-1qv8tlb",
      "type": "seven_select",
      "shapeIssues": [],
      "updatedAt": "2026-06-17T22:41:02.476Z"
    },
    "seven_select-sp-高考-1r3zfjm": {
      "rowId": "seven_select-sp-高考-1r3zfjm",
      "type": "seven_select",
      "shapeIssues": [],
      "updatedAt": "2026-06-17T22:41:02.477Z"
    },
    "seven_select-sp-高考-1rrn6y": {
      "rowId": "seven_select-sp-高考-1rrn6y",
      "type": "seven_select",
      "shapeIssues": [],
      "updatedAt": "2026-06-17T22:41:02.477Z"
    },
    "seven_select-sp-高考-1sxxgk1": {
      "rowId": "seven_select-sp-高考-1sxxgk1",
      "type": "seven_select",
      "shapeIssues": [],
      "updatedAt": "2026-06-17T22:41:02.478Z"
    },
    "seven_select-sp-高考-1t2rt67": {
      "rowId": "seven_select-sp-高考-1t2rt67",
      "type": "seven_select",
      "shapeIssues": [],
      "updatedAt": "2026-06-17T22:41:02.479Z"
    },
    "seven_select-sp-高考-1ueacqa": {
      "rowId": "seven_select-sp-高考-1ueacqa",
      "type": "seven_select",
      "shapeIssues": [],
      "updatedAt": "2026-06-17T22:41:02.479Z"
    },
    "seven_select-sp-高考-1v3xdy7": {
      "rowId": "seven_select-sp-高考-1v3xdy7",
      "type": "seven_select",
      "shapeIssues": [],
      "updatedAt": "2026-06-17T22:41:02.480Z"
    },
    "seven_select-sp-高考-1vn3uu7": {
      "rowId": "seven_select-sp-高考-1vn3uu7",
      "type": "seven_select",
      "shapeIssues": [],
      "updatedAt": "2026-06-17T22:41:02.481Z"
    },
    "seven_select-sp-高考-1w0pxfg": {
      "rowId": "seven_select-sp-高考-1w0pxfg",
      "type": "seven_select",
      "shapeIssues": [],
      "updatedAt": "2026-06-17T22:41:02.481Z"
    },
    "seven_select-sp-高考-1w3q0bq": {
      "rowId": "seven_select-sp-高考-1w3q0bq",
      "type": "seven_select",
      "shapeIssues": [],
      "updatedAt": "2026-06-17T22:41:02.482Z"
    },
    "seven_select-sp-高考-1wmkzoc": {
      "rowId": "seven_select-sp-高考-1wmkzoc",
      "type": "seven_select",
      "shapeIssues": [],
      "updatedAt": "2026-06-17T22:41:02.483Z"
    },
    "seven_select-sp-高考-1xg38uj": {
      "rowId": "seven_select-sp-高考-1xg38uj",
      "type": "seven_select",
      "shapeIssues": [],
      "updatedAt": "2026-06-17T22:41:02.483Z"
    },
    "seven_select-sp-高考-1y3kq28": {
      "rowId": "seven_select-sp-高考-1y3kq28",
      "type": "seven_select",
      "shapeIssues": [],
      "updatedAt": "2026-06-17T22:41:02.484Z"
    },
    "seven_select-sp-高考-349evs": {
      "rowId": "seven_select-sp-高考-349evs",
      "type": "seven_select",
      "shapeIssues": [],
      "updatedAt": "2026-06-17T22:41:02.485Z"
    },
    "seven_select-sp-高考-4bitly": {
      "rowId": "seven_select-sp-高考-4bitly",
      "type": "seven_select",
      "shapeIssues": [],
      "updatedAt": "2026-06-17T22:41:02.485Z"
    },
    "seven_select-sp-高考-6vri7q": {
      "rowId": "seven_select-sp-高考-6vri7q",
      "type": "seven_select",
      "shapeIssues": [],
      "updatedAt": "2026-06-17T22:41:02.486Z"
    },
    "seven_select-sp-高考-7e4uu4": {
      "rowId": "seven_select-sp-高考-7e4uu4",
      "type": "seven_select",
      "shapeIssues": [],
      "updatedAt": "2026-06-17T22:41:02.487Z"
    },
    "seven_select-sp-高考-7uz8s9": {
      "rowId": "seven_select-sp-高考-7uz8s9",
      "type": "seven_select",
      "shapeIssues": [],
      "updatedAt": "2026-06-17T22:41:02.487Z"
    },
    "seven_select-sp-高考-aixxi6": {
      "rowId": "seven_select-sp-高考-aixxi6",
      "type": "seven_select",
      "shapeIssues": [],
      "updatedAt": "2026-06-17T22:41:02.488Z"
    },
    "seven_select-sp-高考-au2i7h": {
      "rowId": "seven_select-sp-高考-au2i7h",
      "type": "seven_select",
      "shapeIssues": [],
      "updatedAt": "2026-06-17T22:41:02.489Z"
    },
    "seven_select-sp-高考-bx8wzf": {
      "rowId": "seven_select-sp-高考-bx8wzf",
      "type": "seven_select",
      "shapeIssues": [],
      "updatedAt": "2026-06-17T22:41:02.490Z"
    },
    "seven_select-sp-高考-ehb9bg": {
      "rowId": "seven_select-sp-高考-ehb9bg",
      "type": "seven_select",
      "shapeIssues": [],
      "updatedAt": "2026-06-17T22:41:02.490Z"
    },
    "seven_select-sp-高考-fzigde": {
      "rowId": "seven_select-sp-高考-fzigde",
      "type": "seven_select",
      "shapeIssues": [],
      "updatedAt": "2026-06-17T22:41:02.491Z"
    },
    "seven_select-sp-高考-gu8ahg": {
      "rowId": "seven_select-sp-高考-gu8ahg",
      "type": "seven_select",
      "shapeIssues": [],
      "updatedAt": "2026-06-17T22:41:02.492Z"
    },
    "seven_select-sp-高考-gzclpr": {
      "rowId": "seven_select-sp-高考-gzclpr",
      "type": "seven_select",
      "shapeIssues": [],
      "updatedAt": "2026-06-17T22:41:02.492Z"
    },
    "seven_select-sp-高考-hv9kh7": {
      "rowId": "seven_select-sp-高考-hv9kh7",
      "type": "seven_select",
      "shapeIssues": [],
      "updatedAt": "2026-06-17T22:41:02.493Z"
    },
    "seven_select-sp-高考-ikieod": {
      "rowId": "seven_select-sp-高考-ikieod",
      "type": "seven_select",
      "shapeIssues": [],
      "updatedAt": "2026-06-17T22:41:02.494Z"
    },
    "seven_select-sp-高考-nroew3": {
      "rowId": "seven_select-sp-高考-nroew3",
      "type": "seven_select",
      "shapeIssues": [],
      "updatedAt": "2026-06-17T22:41:02.495Z"
    },
    "seven_select-sp-高考-o84tj6": {
      "rowId": "seven_select-sp-高考-o84tj6",
      "type": "seven_select",
      "shapeIssues": [],
      "updatedAt": "2026-06-17T22:41:02.496Z"
    },
    "seven_select-sp-高考-pg3x8t": {
      "rowId": "seven_select-sp-高考-pg3x8t",
      "type": "seven_select",
      "shapeIssues": [],
      "updatedAt": "2026-06-17T22:41:02.496Z"
    },
    "seven_select-sp-高考-pxulu3": {
      "rowId": "seven_select-sp-高考-pxulu3",
      "type": "seven_select",
      "shapeIssues": [],
      "updatedAt": "2026-06-17T22:41:02.497Z"
    },
    "seven_select-sp-高考-qgob8p": {
      "rowId": "seven_select-sp-高考-qgob8p",
      "type": "seven_select",
      "shapeIssues": [],
      "updatedAt": "2026-06-17T22:41:02.498Z"
    },
    "seven_select-sp-高考-qm7qb9": {
      "rowId": "seven_select-sp-高考-qm7qb9",
      "type": "seven_select",
      "shapeIssues": [],
      "updatedAt": "2026-06-17T22:41:02.498Z"
    },
    "seven_select-sp-高考-ra6a9y": {
      "rowId": "seven_select-sp-高考-ra6a9y",
      "type": "seven_select",
      "shapeIssues": [],
      "updatedAt": "2026-06-17T22:41:02.499Z"
    },
    "seven_select-sp-高考-siydko": {
      "rowId": "seven_select-sp-高考-siydko",
      "type": "seven_select",
      "shapeIssues": [],
      "updatedAt": "2026-06-17T22:41:02.500Z"
    },
    "seven_select-sp-高考-u4w46a": {
      "rowId": "seven_select-sp-高考-u4w46a",
      "type": "seven_select",
      "shapeIssues": [],
      "updatedAt": "2026-06-17T22:41:02.500Z"
    },
    "seven_select-sp-高考-ussxyt": {
      "rowId": "seven_select-sp-高考-ussxyt",
      "type": "seven_select",
      "shapeIssues": [],
      "updatedAt": "2026-06-17T22:41:02.501Z"
    },
    "seven_select-sp-高考-vd6m9u": {
      "rowId": "seven_select-sp-高考-vd6m9u",
      "type": "seven_select",
      "shapeIssues": [],
      "updatedAt": "2026-06-17T22:41:02.502Z"
    },
    "seven_select-sp-高考-xak77k": {
      "rowId": "seven_select-sp-高考-xak77k",
      "type": "seven_select",
      "shapeIssues": [],
      "updatedAt": "2026-06-17T22:41:02.503Z"
    },
    "seven_select-sp-高考-xotdfc": {
      "rowId": "seven_select-sp-高考-xotdfc",
      "type": "seven_select",
      "shapeIssues": [],
      "updatedAt": "2026-06-17T22:41:02.503Z"
    },
    "seven_select-sp-高考-y0vrb5": {
      "rowId": "seven_select-sp-高考-y0vrb5",
      "type": "seven_select",
      "shapeIssues": [],
      "updatedAt": "2026-06-17T22:41:02.504Z"
    },
    "seven_select-sp-高考-zf4w7a": {
      "rowId": "seven_select-sp-高考-zf4w7a",
      "type": "seven_select",
      "shapeIssues": [],
      "updatedAt": "2026-06-17T22:41:02.505Z"
    }
  }
}